{
  "ID": "b2a465c1-8c85-419c-918c-07eaeb6d509d",
  "Version": "3.10.0.0",
  "Name": "Sungura_mjanja_Hare_the_trickster_03",
  "Content": {
    "Content": {
      "Animation": {
        "Duration": 305,
        "Speed": 1.0,
        "ActivedAnimationName": "master",
        "Timelines": [
          {
            "ActionTag": -1365921991,
            "Property": "Position",
            "Frames": [
              {
                "X": 1995.9138,
                "Y": 1026.7578,
                "FrameIndex": 0,
                "EasingData": {
                  "Type": 0
                },
                "ctype": "PointFrameData"
              },
              {
                "X": 725.9028,
                "Y": 1106.7363,
                "FrameIndex": 305,
                "EasingData": {
                  "Type": 0
                },
                "ctype": "PointFrameData"
              }
            ],
            "ctype": "TimelineData"
          },
          {
            "ActionTag": 141080025,
            "Property": "Position",
            "Frames": [
              {
                "X": 1255.6162,
                "Y": 996.7592,
                "FrameIndex": 0,
                "EasingData": {
                  "Type": 0
                },
                "ctype": "PointFrameData"
              },
              {
                "X": -14.3876,
                "Y": 1076.7412,
                "FrameIndex": 305,
                "EasingData": {
                  "Type": 0
                },
                "ctype": "PointFrameData"
              }
            ],
            "ctype": "TimelineData"
          },
          {
            "ActionTag": 23100544,
            "Property": "Position",
            "Frames": [
              {
                "X": 2425.624,
                "Y": 926.7593,
                "FrameIndex": 0,
                "EasingData": {
                  "Type": 0
                },
                "ctype": "PointFrameData"
              },
              {
                "X": 1155.6138,
                "Y": 1006.7424,
                "FrameIndex": 305,
                "EasingData": {
                  "Type": 0
                },
                "ctype": "PointFrameData"
              }
            ],
            "ctype": "TimelineData"
          },
          {
            "ActionTag": 595920041,
            "Property": "Position",
            "Frames": [
              {
                "X": 1545.9141,
                "Y": 936.7585,
                "FrameIndex": 0,
                "EasingData": {
                  "Type": 0
                },
                "ctype": "PointFrameData"
              },
              {
                "X": 275.9036,
                "Y": 1016.7415,
                "FrameIndex": 305,
                "EasingData": {
                  "Type": 0
                },
                "ctype": "PointFrameData"
              }
            ],
            "ctype": "TimelineData"
          },
          {
            "ActionTag": 1737156842,
            "Property": "Position",
            "Frames": [
              {
                "X": 911.5797,
                "Y": 920.2731,
                "FrameIndex": 0,
                "EasingData": {
                  "Type": 0
                },
                "ctype": "PointFrameData"
              },
              {
                "X": -358.4213,
                "Y": 1000.2562,
                "FrameIndex": 305,
                "EasingData": {
                  "Type": 0
                },
                "ctype": "PointFrameData"
              }
            ],
            "ctype": "TimelineData"
          },
          {
            "ActionTag": 1285730987,
            "Property": "Position",
            "Frames": [
              {
                "X": 105.4003,
                "Y": 840.782,
                "FrameIndex": 0,
                "EasingData": {
                  "Type": 0
                },
                "ctype": "PointFrameData"
              },
              {
                "X": -1164.5979,
                "Y": 920.7649,
                "FrameIndex": 305,
                "EasingData": {
                  "Type": 0
                },
                "ctype": "PointFrameData"
              }
            ],
            "ctype": "TimelineData"
          },
          {
            "ActionTag": 766958986,
            "Property": "Position",
            "Frames": [
              {
                "X": 2279.8584,
                "Y": 1537.5549,
                "FrameIndex": 0,
                "EasingData": {
                  "Type": 0
                },
                "ctype": "PointFrameData"
              },
              {
                "X": 1009.8513,
                "Y": 1617.5542,
                "FrameIndex": 305,
                "EasingData": {
                  "Type": 0
                },
                "ctype": "PointFrameData"
              }
            ],
            "ctype": "TimelineData"
          },
          {
            "ActionTag": -431665943,
            "Property": "Position",
            "Frames": [
              {
                "X": 1733.1626,
                "Y": 1553.8303,
                "FrameIndex": 0,
                "EasingData": {
                  "Type": 0
                },
                "ctype": "PointFrameData"
              },
              {
                "X": 463.1561,
                "Y": 1633.8298,
                "FrameIndex": 305,
                "EasingData": {
                  "Type": 0
                },
                "ctype": "PointFrameData"
              }
            ],
            "ctype": "TimelineData"
          },
          {
            "ActionTag": -1637614865,
            "Property": "Position",
            "Frames": [
              {
                "X": 1227.2234,
                "Y": 1550.3989,
                "FrameIndex": 0,
                "EasingData": {
                  "Type": 0
                },
                "ctype": "PointFrameData"
              },
              {
                "X": -42.7811,
                "Y": 1630.3984,
                "FrameIndex": 305,
                "EasingData": {
                  "Type": 0
                },
                "ctype": "PointFrameData"
              }
            ],
            "ctype": "TimelineData"
          },
          {
            "ActionTag": -1687703577,
            "Property": "Position",
            "Frames": [
              {
                "X": 765.2918,
                "Y": 1465.3601,
                "FrameIndex": 0,
                "EasingData": {
                  "Type": 0
                },
                "ctype": "PointFrameData"
              },
              {
                "X": -504.7084,
                "Y": 1545.3557,
                "FrameIndex": 305,
                "EasingData": {
                  "Type": 0
                },
                "ctype": "PointFrameData"
              }
            ],
            "ctype": "TimelineData"
          },
          {
            "ActionTag": -516512990,
            "Property": "Position",
            "Frames": [
              {
                "X": 154.0024,
                "Y": 1544.1917,
                "FrameIndex": 0,
                "EasingData": {
                  "Type": 0
                },
                "ctype": "PointFrameData"
              },
              {
                "X": -1115.9933,
                "Y": 1624.1912,
                "FrameIndex": 305,
                "EasingData": {
                  "Type": 0
                },
                "ctype": "PointFrameData"
              }
            ],
            "ctype": "TimelineData"
          },
          {
            "ActionTag": -413681980,
            "Property": "Position",
            "Frames": [
              {
                "X": 51.9693,
                "Y": 1734.2705,
                "FrameIndex": 0,
                "EasingData": {
                  "Type": 0
                },
                "ctype": "PointFrameData"
              },
              {
                "X": -1218.0269,
                "Y": 1814.2576,
                "FrameIndex": 305,
                "EasingData": {
                  "Type": 0
                },
                "ctype": "PointFrameData"
              }
            ],
            "ctype": "TimelineData"
          },
          {
            "ActionTag": -1672708763,
            "Property": "Position",
            "Frames": [
              {
                "X": 626.9213,
                "Y": 1684.8564,
                "FrameIndex": 0,
                "EasingData": {
                  "Type": 0
                },
                "ctype": "PointFrameData"
              },
              {
                "X": -643.0782,
                "Y": 1764.8506,
                "FrameIndex": 305,
                "EasingData": {
                  "Type": 0
                },
                "ctype": "PointFrameData"
              }
            ],
            "ctype": "TimelineData"
          },
          {
            "ActionTag": -2102719016,
            "Property": "Position",
            "Frames": [
              {
                "X": 1191.8682,
                "Y": 1606.0271,
                "FrameIndex": 0,
                "EasingData": {
                  "Type": 0
                },
                "ctype": "PointFrameData"
              },
              {
                "X": -78.1369,
                "Y": 1686.0271,
                "FrameIndex": 305,
                "EasingData": {
                  "Type": 0
                },
                "ctype": "PointFrameData"
              }
            ],
            "ctype": "TimelineData"
          },
          {
            "ActionTag": 151946196,
            "Property": "Position",
            "Frames": [
              {
                "X": 1783.0977,
                "Y": 1711.1345,
                "FrameIndex": 0,
                "EasingData": {
                  "Type": 0
                },
                "ctype": "PointFrameData"
              },
              {
                "X": 513.0889,
                "Y": 1791.1265,
                "FrameIndex": 305,
                "EasingData": {
                  "Type": 0
                },
                "ctype": "PointFrameData"
              }
            ],
            "ctype": "TimelineData"
          },
          {
            "ActionTag": 883044619,
            "Property": "Position",
            "Frames": [
              {
                "X": 2374.3215,
                "Y": 1619.1655,
                "FrameIndex": 0,
                "EasingData": {
                  "Type": 0
                },
                "ctype": "PointFrameData"
              },
              {
                "X": 1104.3071,
                "Y": 1699.1655,
                "FrameIndex": 305,
                "EasingData": {
                  "Type": 0
                },
                "ctype": "PointFrameData"
              }
            ],
            "ctype": "TimelineData"
          },
          {
            "ActionTag": 104899481,
            "Property": "Position",
            "Frames": [
              {
                "X": 127.4625,
                "Y": 1640.1799,
                "FrameIndex": 0,
                "EasingData": {
                  "Type": 0
                },
                "ctype": "PointFrameData"
              },
              {
                "X": -1142.5355,
                "Y": 1720.1763,
                "FrameIndex": 305,
                "EasingData": {
                  "Type": 0
                },
                "ctype": "PointFrameData"
              }
            ],
            "ctype": "TimelineData"
          },
          {
            "ActionTag": -1279852446,
            "Property": "Position",
            "Frames": [
              {
                "X": 729.8835,
                "Y": 1558.9592,
                "FrameIndex": 0,
                "EasingData": {
                  "Type": 0
                },
                "ctype": "PointFrameData"
              },
              {
                "X": -540.1161,
                "Y": 1638.9592,
                "FrameIndex": 305,
                "EasingData": {
                  "Type": 0
                },
                "ctype": "PointFrameData"
              }
            ],
            "ctype": "TimelineData"
          },
          {
            "ActionTag": -1192212441,
            "Property": "Position",
            "Frames": [
              {
                "X": 1487.4041,
                "Y": 1601.3323,
                "FrameIndex": 0,
                "EasingData": {
                  "Type": 0
                },
                "ctype": "PointFrameData"
              },
              {
                "X": 217.4016,
                "Y": 1681.3323,
                "FrameIndex": 305,
                "EasingData": {
                  "Type": 0
                },
                "ctype": "PointFrameData"
              }
            ],
            "ctype": "TimelineData"
          },
          {
            "ActionTag": -15869098,
            "Property": "Position",
            "Frames": [
              {
                "X": 2213.7778,
                "Y": 1601.3323,
                "FrameIndex": 0,
                "EasingData": {
                  "Type": 0
                },
                "ctype": "PointFrameData"
              },
              {
                "X": 943.7612,
                "Y": 1681.3323,
                "FrameIndex": 305,
                "EasingData": {
                  "Type": 0
                },
                "ctype": "PointFrameData"
              }
            ],
            "ctype": "TimelineData"
          },
          {
            "ActionTag": -998079649,
            "Property": "ActionValue",
            "Frames": [
              {
                "InnerActionType": "LoopAction",
                "CurrentAniamtionName": "walk",
                "SingleFrameIndex": 0,
                "FrameIndex": 0,
                "Tween": false,
                "ctype": "InnerActionFrameData"
              },
              {
                "InnerActionType": "LoopAction",
                "CurrentAniamtionName": "walk",
                "SingleFrameIndex": 0,
                "FrameIndex": 305,
                "Tween": false,
                "ctype": "InnerActionFrameData"
              }
            ],
            "ctype": "TimelineData"
          },
          {
            "ActionTag": -998079649,
            "Property": "Position",
            "Frames": [
              {
                "X": -244.2826,
                "Y": 96.5065,
                "FrameIndex": 0,
                "EasingData": {
                  "Type": 0
                },
                "ctype": "PointFrameData"
              },
              {
                "X": 601.4446,
                "Y": 101.5276,
                "FrameIndex": 305,
                "EasingData": {
                  "Type": 0
                },
                "ctype": "PointFrameData"
              }
            ],
            "ctype": "TimelineData"
          },
          {
            "ActionTag": -998079649,
            "Property": "Scale",
            "Frames": [
              {
                "X": -1.0,
                "Y": 1.0,
                "FrameIndex": 0,
                "EasingData": {
                  "Type": 0
                },
                "ctype": "ScaleValueFrameData"
              },
              {
                "X": -1.0,
                "Y": 1.0,
                "FrameIndex": 305,
                "EasingData": {
                  "Type": 0
                },
                "ctype": "ScaleValueFrameData"
              }
            ],
            "ctype": "TimelineData"
          },
          {
            "ActionTag": -998079649,
            "Property": "RotationSkew",
            "Frames": [
              {
                "X": 0.0,
                "Y": 0.0,
                "FrameIndex": 0,
                "EasingData": {
                  "Type": 0
                },
                "ctype": "ScaleValueFrameData"
              },
              {
                "X": 0.0,
                "Y": 0.0,
                "FrameIndex": 305,
                "EasingData": {
                  "Type": 0
                },
                "ctype": "ScaleValueFrameData"
              }
            ],
            "ctype": "TimelineData"
          },
          {
            "ActionTag": -582220063,
            "Property": "Position",
            "Frames": [
              {
                "X": -202.2006,
                "Y": 845.8993,
                "FrameIndex": 0,
                "EasingData": {
                  "Type": 0
                },
                "ctype": "PointFrameData"
              },
              {
                "X": 698.6483,
                "Y": 870.5889,
                "FrameIndex": 305,
                "EasingData": {
                  "Type": 0
                },
                "ctype": "PointFrameData"
              }
            ],
            "ctype": "TimelineData"
          },
          {
            "ActionTag": -582220063,
            "Property": "FileData",
            "Frames": [
              {
                "TextureFile": {
                  "Type": "MarkedSubImage",
                  "Path": "Sungura_mjanja_Hare_the_trickster/pot.png",
                  "Plist": "Sungura_mjanja_Hare_the_trickster/Sungura_mjanja_Hare_the_trickster.plist"
                },
                "FrameIndex": 0,
                "Tween": false,
                "ctype": "TextureFrameData"
              }
            ],
            "ctype": "TimelineData"
          },
          {
            "ActionTag": -582220063,
            "Property": "BlendFunc",
            "Frames": [
              {
                "Src": 1,
                "Dst": 771,
                "FrameIndex": 0,
                "Tween": false,
                "ctype": "BlendFuncFrameData"
              }
            ],
            "ctype": "TimelineData"
          },
          {
            "ActionTag": -2076227950,
            "Property": "Position",
            "Frames": [
              {
                "X": 4995.8901,
                "Y": 936.7469,
                "FrameIndex": 0,
                "EasingData": {
                  "Type": 0
                },
                "ctype": "PointFrameData"
              },
              {
                "X": 3725.8579,
                "Y": 1016.7299,
                "FrameIndex": 305,
                "EasingData": {
                  "Type": 0
                },
                "ctype": "PointFrameData"
              }
            ],
            "ctype": "TimelineData"
          },
          {
            "ActionTag": -91299094,
            "Property": "Position",
            "Frames": [
              {
                "X": 4255.6069,
                "Y": 906.75,
                "FrameIndex": 0,
                "EasingData": {
                  "Type": 0
                },
                "ctype": "PointFrameData"
              },
              {
                "X": 2985.5818,
                "Y": 986.7329,
                "FrameIndex": 305,
                "EasingData": {
                  "Type": 0
                },
                "ctype": "PointFrameData"
              }
            ],
            "ctype": "TimelineData"
          },
          {
            "ActionTag": -266901448,
            "Property": "Position",
            "Frames": [
              {
                "X": 5425.5854,
                "Y": 836.7534,
                "FrameIndex": 0,
                "EasingData": {
                  "Type": 0
                },
                "ctype": "PointFrameData"
              },
              {
                "X": 4155.5444,
                "Y": 916.7363,
                "FrameIndex": 305,
                "EasingData": {
                  "Type": 0
                },
                "ctype": "PointFrameData"
              }
            ],
            "ctype": "TimelineData"
          },
          {
            "ActionTag": 1983037331,
            "Property": "Position",
            "Frames": [
              {
                "X": 4545.9048,
                "Y": 846.7518,
                "FrameIndex": 0,
                "EasingData": {
                  "Type": 0
                },
                "ctype": "PointFrameData"
              },
              {
                "X": 3275.8799,
                "Y": 926.7347,
                "FrameIndex": 305,
                "EasingData": {
                  "Type": 0
                },
                "ctype": "PointFrameData"
              }
            ],
            "ctype": "TimelineData"
          },
          {
            "ActionTag": -21325491,
            "Property": "Position",
            "Frames": [
              {
                "X": 3911.5225,
                "Y": 830.2684,
                "FrameIndex": 0,
                "EasingData": {
                  "Type": 0
                },
                "ctype": "PointFrameData"
              },
              {
                "X": 2641.4634,
                "Y": 910.2513,
                "FrameIndex": 305,
                "EasingData": {
                  "Type": 0
                },
                "ctype": "PointFrameData"
              }
            ],
            "ctype": "TimelineData"
          },
          {
            "ActionTag": -1306158871,
            "Property": "Position",
            "Frames": [
              {
                "X": 5279.7612,
                "Y": 1447.5432,
                "FrameIndex": 0,
                "EasingData": {
                  "Type": 0
                },
                "ctype": "PointFrameData"
              },
              {
                "X": 4009.6982,
                "Y": 1527.5371,
                "FrameIndex": 305,
                "EasingData": {
                  "Type": 0
                },
                "ctype": "PointFrameData"
              }
            ],
            "ctype": "TimelineData"
          },
          {
            "ActionTag": -1406668354,
            "Property": "Position",
            "Frames": [
              {
                "X": 4733.0859,
                "Y": 1463.8184,
                "FrameIndex": 0,
                "EasingData": {
                  "Type": 0
                },
                "ctype": "PointFrameData"
              },
              {
                "X": 3463.0454,
                "Y": 1543.814,
                "FrameIndex": 305,
                "EasingData": {
                  "Type": 0
                },
                "ctype": "PointFrameData"
              }
            ],
            "ctype": "TimelineData"
          },
          {
            "ActionTag": 474636400,
            "Property": "Position",
            "Frames": [
              {
                "X": 4227.1772,
                "Y": 1460.387,
                "FrameIndex": 0,
                "EasingData": {
                  "Type": 0
                },
                "ctype": "PointFrameData"
              },
              {
                "X": 2957.1536,
                "Y": 1540.3813,
                "FrameIndex": 305,
                "EasingData": {
                  "Type": 0
                },
                "ctype": "PointFrameData"
              }
            ],
            "ctype": "TimelineData"
          },
          {
            "ActionTag": -467463433,
            "Property": "Position",
            "Frames": [
              {
                "X": 3765.2524,
                "Y": 1375.355,
                "FrameIndex": 0,
                "EasingData": {
                  "Type": 0
                },
                "ctype": "PointFrameData"
              },
              {
                "X": 2495.2212,
                "Y": 1455.3508,
                "FrameIndex": 305,
                "EasingData": {
                  "Type": 0
                },
                "ctype": "PointFrameData"
              }
            ],
            "ctype": "TimelineData"
          },
          {
            "ActionTag": -828869116,
            "Property": "Position",
            "Frames": [
              {
                "X": 3626.8955,
                "Y": 1594.843,
                "FrameIndex": 0,
                "EasingData": {
                  "Type": 0
                },
                "ctype": "PointFrameData"
              },
              {
                "X": 2356.8411,
                "Y": 1674.843,
                "FrameIndex": 305,
                "EasingData": {
                  "Type": 0
                },
                "ctype": "PointFrameData"
              }
            ],
            "ctype": "TimelineData"
          },
          {
            "ActionTag": -1778102008,
            "Property": "Position",
            "Frames": [
              {
                "X": 4191.8545,
                "Y": 1516.0186,
                "FrameIndex": 0,
                "EasingData": {
                  "Type": 0
                },
                "ctype": "PointFrameData"
              },
              {
                "X": 2921.7947,
                "Y": 1596.0186,
                "FrameIndex": 305,
                "EasingData": {
                  "Type": 0
                },
                "ctype": "PointFrameData"
              }
            ],
            "ctype": "TimelineData"
          },
          {
            "ActionTag": -550151510,
            "Property": "Position",
            "Frames": [
              {
                "X": 4783.0923,
                "Y": 1621.1187,
                "FrameIndex": 0,
                "EasingData": {
                  "Type": 0
                },
                "ctype": "PointFrameData"
              },
              {
                "X": 3513.0322,
                "Y": 1701.1174,
                "FrameIndex": 305,
                "EasingData": {
                  "Type": 0
                },
                "ctype": "PointFrameData"
              }
            ],
            "ctype": "TimelineData"
          },
          {
            "ActionTag": -905981365,
            "Property": "Position",
            "Frames": [
              {
                "X": 5374.3086,
                "Y": 1529.157,
                "FrameIndex": 0,
                "EasingData": {
                  "Type": 0
                },
                "ctype": "PointFrameData"
              },
              {
                "X": 4104.2861,
                "Y": 1609.157,
                "FrameIndex": 305,
                "EasingData": {
                  "Type": 0
                },
                "ctype": "PointFrameData"
              }
            ],
            "ctype": "TimelineData"
          },
          {
            "ActionTag": 569461126,
            "Property": "Position",
            "Frames": [
              {
                "X": 3729.8398,
                "Y": 1468.9465,
                "FrameIndex": 0,
                "EasingData": {
                  "Type": 0
                },
                "ctype": "PointFrameData"
              },
              {
                "X": 2459.8093,
                "Y": 1548.9458,
                "FrameIndex": 305,
                "EasingData": {
                  "Type": 0
                },
                "ctype": "PointFrameData"
              }
            ],
            "ctype": "TimelineData"
          },
          {
            "ActionTag": 1364796223,
            "Property": "Position",
            "Frames": [
              {
                "X": 4487.3677,
                "Y": 1511.3157,
                "FrameIndex": 0,
                "EasingData": {
                  "Type": 0
                },
                "ctype": "PointFrameData"
              },
              {
                "X": 3217.3213,
                "Y": 1591.3152,
                "FrameIndex": 305,
                "EasingData": {
                  "Type": 0
                },
                "ctype": "PointFrameData"
              }
            ],
            "ctype": "TimelineData"
          },
          {
            "ActionTag": 1649610432,
            "Property": "Position",
            "Frames": [
              {
                "X": 5213.7324,
                "Y": 1511.3157,
                "FrameIndex": 0,
                "EasingData": {
                  "Type": 0
                },
                "ctype": "PointFrameData"
              },
              {
                "X": 3943.6733,
                "Y": 1591.3152,
                "FrameIndex": 305,
                "EasingData": {
                  "Type": 0
                },
                "ctype": "PointFrameData"
              }
            ],
            "ctype": "TimelineData"
          },
          {
            "ActionTag": 770026957,
            "Property": "ActionValue",
            "Frames": [
              {
                "InnerActionType": "LoopAction",
                "CurrentAniamtionName": "fly",
                "SingleFrameIndex": 0,
                "FrameIndex": 0,
                "Tween": false,
                "ctype": "InnerActionFrameData"
              }
            ],
            "ctype": "TimelineData"
          },
          {
            "ActionTag": 770026957,
            "Property": "Position",
            "Frames": [
              {
                "X": 3289.396,
                "Y": 1080.8489,
                "FrameIndex": 0,
                "EasingData": {
                  "Type": 0
                },
                "ctype": "PointFrameData"
              },
              {
                "X": -929.7863,
                "Y": 1056.6272,
                "FrameIndex": 305,
                "EasingData": {
                  "Type": 0
                },
                "ctype": "PointFrameData"
              }
            ],
            "ctype": "TimelineData"
          },
          {
            "ActionTag": 770026957,
            "Property": "Scale",
            "Frames": [
              {
                "X": 1.0,
                "Y": 1.0,
                "FrameIndex": 0,
                "EasingData": {
                  "Type": 0
                },
                "ctype": "ScaleValueFrameData"
              }
            ],
            "ctype": "TimelineData"
          },
          {
            "ActionTag": 770026957,
            "Property": "RotationSkew",
            "Frames": [
              {
                "X": 0.0,
                "Y": 0.0,
                "FrameIndex": 0,
                "EasingData": {
                  "Type": 0
                },
                "ctype": "ScaleValueFrameData"
              }
            ],
            "ctype": "TimelineData"
          },
          {
            "ActionTag": -2108197269,
            "Property": "ActionValue",
            "Frames": [
              {
                "InnerActionType": "SingleFrame",
                "CurrentAniamtionName": "hop",
                "SingleFrameIndex": 0,
                "FrameIndex": 0,
                "Tween": false,
                "ctype": "InnerActionFrameData"
              },
              {
                "InnerActionType": "LoopAction",
                "CurrentAniamtionName": "hop",
                "SingleFrameIndex": 0,
                "FrameIndex": 305,
                "Tween": false,
                "ctype": "InnerActionFrameData"
              }
            ],
            "ctype": "TimelineData"
          },
          {
            "ActionTag": -2108197269,
            "Property": "Position",
            "Frames": [
              {
                "X": -326.9784,
                "Y": 766.5491,
                "FrameIndex": 0,
                "EasingData": {
                  "Type": 0
                },
                "ctype": "PointFrameData"
              },
              {
                "X": 574.0405,
                "Y": 802.893,
                "FrameIndex": 305,
                "EasingData": {
                  "Type": 0
                },
                "ctype": "PointFrameData"
              }
            ],
            "ctype": "TimelineData"
          },
          {
            "ActionTag": -2108197269,
            "Property": "Scale",
            "Frames": [
              {
                "X": -0.5438,
                "Y": 0.5438,
                "FrameIndex": 0,
                "EasingData": {
                  "Type": 0
                },
                "ctype": "ScaleValueFrameData"
              },
              {
                "X": -0.5438,
                "Y": 0.5438,
                "FrameIndex": 305,
                "EasingData": {
                  "Type": 0
                },
                "ctype": "ScaleValueFrameData"
              }
            ],
            "ctype": "TimelineData"
          },
          {
            "ActionTag": -2108197269,
            "Property": "RotationSkew",
            "Frames": [
              {
                "X": 0.0,
                "Y": 0.0,
                "FrameIndex": 0,
                "EasingData": {
                  "Type": 0
                },
                "ctype": "ScaleValueFrameData"
              },
              {
                "X": 0.0,
                "Y": 0.0,
                "FrameIndex": 305,
                "EasingData": {
                  "Type": 0
                },
                "ctype": "ScaleValueFrameData"
              }
            ],
            "ctype": "TimelineData"
          }
        ],
        "ctype": "TimelineActionData"
      },
      "AnimationList": [
        {
          "StartIndex": 0,
          "EndIndex": 305,
          "Name": "master",
          "ctype": "AnimationInfoData"
        }
      ],
      "ObjectData": {
        "Tag": 17,
        "Children": [
          {
            "ClipAble": false,
            "ComboBoxIndex": 1,
            "SingleColor": {
              "R": 165,
              "G": 213,
              "B": 162
            },
            "FirstColor": {
              "R": 150,
              "G": 200
            },
            "EndColor": {},
            "ColorVector": {
              "ScaleY": 1.0
            },
            "Scale9Width": 1,
            "Scale9Height": 1,
            "TouchEnable": true,
            "AnchorPoint": {},
            "Position": {
              "X": -223.3496,
              "Y": -118.2449
            },
            "Scale": {
              "ScaleX": 15.1895,
              "ScaleY": 10.0327
            },
            "CColor": {},
            "IconVisible": false,
            "PrePosition": {
              "X": -0.0872,
              "Y": -0.0657
            },
            "PreSize": {
              "X": 0.0781,
              "Y": 0.1111
            },
            "LeftMargin": -223.3496,
            "RightMargin": 2583.3496,
            "TopMargin": 1718.2449,
            "BottomMargin": -118.2449,
            "Tag": 32,
            "ActionTag": 1792982495,
            "Size": {
              "X": 200.0,
              "Y": 200.0
            },
            "Name": "Panel_1",
            "ctype": "PanelObjectData"
          },
          {
            "ClipAble": false,
            "ComboBoxIndex": 1,
            "SingleColor": {
              "R": 128,
              "G": 219,
              "B": 122
            },
            "FirstColor": {
              "R": 150,
              "G": 200
            },
            "EndColor": {},
            "ColorVector": {
              "ScaleY": 1.0
            },
            "Scale9Width": 1,
            "Scale9Height": 1,
            "TouchEnable": true,
            "AnchorPoint": {},
            "Position": {
              "X": -711.2482,
              "Y": -275.2699
            },
            "Scale": {
              "ScaleX": 18.4742,
              "ScaleY": 4.1861
            },
            "CColor": {},
            "IconVisible": false,
            "PrePosition": {
              "X": -0.2778,
              "Y": -0.1529
            },
            "PreSize": {
              "X": 0.0781,
              "Y": 0.1111
            },
            "LeftMargin": -711.2482,
            "RightMargin": 3071.2483,
            "TopMargin": 1875.2699,
            "BottomMargin": -275.2699,
            "Tag": 55,
            "ActionTag": 1690729190,
            "Size": {
              "X": 200.0,
              "Y": 200.0
            },
            "Name": "Panel_2",
            "ctype": "PanelObjectData"
          },
          {
            "FileData": {
              "Type": "MarkedSubImage",
              "Path": "Sungura_mjanja_Hare_the_trickster/2-02.png",
              "Plist": "Sungura_mjanja_Hare_the_trickster/Sungura_mjanja_Hare_the_trickster.plist"
            },
            "BlendFunc": {
              "Src": 1,
              "Dst": 771
            },
            "AnchorPoint": {
              "ScaleX": 0.5,
              "ScaleY": 0.5
            },
            "Position": {
              "X": 1995.9138,
              "Y": 1026.7578
            },
            "Scale": {
              "ScaleX": 1.0,
              "ScaleY": 1.0
            },
            "CColor": {},
            "IconVisible": false,
            "PrePosition": {
              "X": 0.7797,
              "Y": 0.5704
            },
            "PreSize": {
              "X": 0.0582,
              "Y": 0.5883
            },
            "LeftMargin": 1921.4138,
            "RightMargin": 489.5862,
            "TopMargin": 243.7422,
            "BottomMargin": 497.2578,
            "Tag": 54,
            "ActionTag": -1365921991,
            "Size": {
              "X": 149.0,
              "Y": 1059.0
            },
            "Name": "Sprite_15_1",
            "ctype": "SpriteObjectData"
          },
          {
            "FileData": {
              "Type": "MarkedSubImage",
              "Path": "Sungura_mjanja_Hare_the_trickster/2-02.png",
              "Plist": "Sungura_mjanja_Hare_the_trickster/Sungura_mjanja_Hare_the_trickster.plist"
            },
            "BlendFunc": {
              "Src": 1,
              "Dst": 771
            },
            "AnchorPoint": {
              "ScaleX": 0.5,
              "ScaleY": 0.5
            },
            "Position": {
              "X": 1255.6162,
              "Y": 996.7592
            },
            "Scale": {
              "ScaleX": 1.0,
              "ScaleY": 1.0
            },
            "CColor": {},
            "IconVisible": false,
            "PrePosition": {
              "X": 0.4905,
              "Y": 0.5538
            },
            "PreSize": {
              "X": 0.0582,
              "Y": 0.5883
            },
            "LeftMargin": 1181.1162,
            "RightMargin": 1229.8838,
            "TopMargin": 273.7407,
            "BottomMargin": 467.2592,
            "Tag": 53,
            "ActionTag": 141080025,
            "Size": {
              "X": 149.0,
              "Y": 1059.0
            },
            "Name": "Sprite_15_0",
            "ctype": "SpriteObjectData"
          },
          {
            "FileData": {
              "Type": "MarkedSubImage",
              "Path": "Sungura_mjanja_Hare_the_trickster/2-02.png",
              "Plist": "Sungura_mjanja_Hare_the_trickster/Sungura_mjanja_Hare_the_trickster.plist"
            },
            "BlendFunc": {
              "Src": 1,
              "Dst": 771
            },
            "AnchorPoint": {
              "ScaleX": 0.5,
              "ScaleY": 0.5
            },
            "Position": {
              "X": 2425.624,
              "Y": 926.7593
            },
            "Scale": {
              "ScaleX": 1.0,
              "ScaleY": 1.0
            },
            "CColor": {},
            "IconVisible": false,
            "PrePosition": {
              "X": 0.9475,
              "Y": 0.5149
            },
            "PreSize": {
              "X": 0.0582,
              "Y": 0.5883
            },
            "LeftMargin": 2351.124,
            "RightMargin": 59.876,
            "TopMargin": 343.7407,
            "BottomMargin": 397.2593,
            "Tag": 33,
            "ActionTag": 23100544,
            "Size": {
              "X": 149.0,
              "Y": 1059.0
            },
            "Name": "Sprite_15",
            "ctype": "SpriteObjectData"
          },
          {
            "FileData": {
              "Type": "MarkedSubImage",
              "Path": "Sungura_mjanja_Hare_the_trickster/2-03.png",
              "Plist": "Sungura_mjanja_Hare_the_trickster/Sungura_mjanja_Hare_the_trickster.plist"
            },
            "BlendFunc": {
              "Src": 1,
              "Dst": 771
            },
            "AnchorPoint": {
              "ScaleX": 0.5,
              "ScaleY": 0.5
            },
            "Position": {
              "X": 1545.9141,
              "Y": 936.7585
            },
            "Scale": {
              "ScaleX": 1.0,
              "ScaleY": 1.0
            },
            "CColor": {},
            "IconVisible": false,
            "PrePosition": {
              "X": 0.6039,
              "Y": 0.5204
            },
            "PreSize": {
              "X": 0.0582,
              "Y": 0.5578
            },
            "LeftMargin": 1471.4141,
            "RightMargin": 939.5859,
            "TopMargin": 361.2415,
            "BottomMargin": 434.7585,
            "Tag": 34,
            "ActionTag": 595920041,
            "Size": {
              "X": 149.0,
              "Y": 1004.0
            },
            "Name": "Sprite_16",
            "ctype": "SpriteObjectData"
          },
          {
            "FileData": {
              "Type": "MarkedSubImage",
              "Path": "Sungura_mjanja_Hare_the_trickster/2-04.png",
              "Plist": "Sungura_mjanja_Hare_the_trickster/Sungura_mjanja_Hare_the_trickster.plist"
            },
            "BlendFunc": {
              "Src": 1,
              "Dst": 771
            },
            "AnchorPoint": {
              "ScaleX": 0.5,
              "ScaleY": 0.5
            },
            "Position": {
              "X": 911.5797,
              "Y": 920.2731
            },
            "Scale": {
              "ScaleX": 1.0,
              "ScaleY": 1.0
            },
            "CColor": {},
            "IconVisible": false,
            "PrePosition": {
              "X": 0.3561,
              "Y": 0.5113
            },
            "PreSize": {
              "X": 0.2387,
              "Y": 0.5833
            },
            "LeftMargin": 606.0797,
            "RightMargin": 1342.9203,
            "TopMargin": 354.7269,
            "BottomMargin": 395.2731,
            "Tag": 35,
            "ActionTag": 1737156842,
            "Size": {
              "X": 611.0,
              "Y": 1050.0
            },
            "Name": "Sprite_17",
            "ctype": "SpriteObjectData"
          },
          {
            "FileData": {
              "Type": "MarkedSubImage",
              "Path": "Sungura_mjanja_Hare_the_trickster/2-05.png",
              "Plist": "Sungura_mjanja_Hare_the_trickster/Sungura_mjanja_Hare_the_trickster.plist"
            },
            "BlendFunc": {
              "Src": 1,
              "Dst": 771
            },
            "AnchorPoint": {
              "ScaleX": 0.5,
              "ScaleY": 0.5
            },
            "Position": {
              "X": 105.4003,
              "Y": 840.782
            },
            "Scale": {
              "ScaleX": 1.0,
              "ScaleY": 1.0
            },
            "CColor": {},
            "IconVisible": false,
            "PrePosition": {
              "X": 0.0412,
              "Y": 0.4671
            },
            "PreSize": {
              "X": 0.2645,
              "Y": 0.6033
            },
            "LeftMargin": -233.0997,
            "RightMargin": 2116.0996,
            "TopMargin": 416.218,
            "BottomMargin": 297.782,
            "Tag": 36,
            "ActionTag": 1285730987,
            "Size": {
              "X": 677.0,
              "Y": 1086.0
            },
            "Name": "Sprite_18",
            "ctype": "SpriteObjectData"
          },
          {
            "FileData": {
              "Type": "MarkedSubImage",
              "Path": "Sungura_mjanja_Hare_the_trickster/2-08.png",
              "Plist": "Sungura_mjanja_Hare_the_trickster/Sungura_mjanja_Hare_the_trickster.plist"
            },
            "BlendFunc": {
              "Src": 1,
              "Dst": 771
            },
            "AnchorPoint": {
              "ScaleX": 0.5,
              "ScaleY": 0.5
            },
            "Position": {
              "X": 2279.8584,
              "Y": 1537.5549
            },
            "Scale": {
              "ScaleX": 1.0341,
              "ScaleY": 1.0
            },
            "CColor": {},
            "IconVisible": false,
            "PrePosition": {
              "X": 0.8906,
              "Y": 0.8542
            },
            "PreSize": {
              "X": 0.2508,
              "Y": 0.2783
            },
            "LeftMargin": 1958.8584,
            "RightMargin": -40.8584,
            "TopMargin": 11.9451,
            "BottomMargin": 1287.0549,
            "Tag": 39,
            "ActionTag": 766958986,
            "Size": {
              "X": 642.0,
              "Y": 501.0
            },
            "Name": "Sprite_21",
            "ctype": "SpriteObjectData"
          },
          {
            "FileData": {
              "Type": "MarkedSubImage",
              "Path": "Sungura_mjanja_Hare_the_trickster/2-08.png",
              "Plist": "Sungura_mjanja_Hare_the_trickster/Sungura_mjanja_Hare_the_trickster.plist"
            },
            "BlendFunc": {
              "Src": 1,
              "Dst": 771
            },
            "AnchorPoint": {
              "ScaleX": 0.5,
              "ScaleY": 0.5
            },
            "Position": {
              "X": 1733.1626,
              "Y": 1553.8303
            },
            "Scale": {
              "ScaleX": 1.0341,
              "ScaleY": 1.0
            },
            "CColor": {},
            "IconVisible": false,
            "PrePosition": {
              "X": 0.677,
              "Y": 0.8632
            },
            "PreSize": {
              "X": 0.2508,
              "Y": 0.2783
            },
            "LeftMargin": 1412.1626,
            "RightMargin": 505.8374,
            "TopMargin": -4.3303,
            "BottomMargin": 1303.3303,
            "Tag": 40,
            "ActionTag": -431665943,
            "Size": {
              "X": 642.0,
              "Y": 501.0
            },
            "Name": "Sprite_21_0",
            "ctype": "SpriteObjectData"
          },
          {
            "FileData": {
              "Type": "MarkedSubImage",
              "Path": "Sungura_mjanja_Hare_the_trickster/2-08.png",
              "Plist": "Sungura_mjanja_Hare_the_trickster/Sungura_mjanja_Hare_the_trickster.plist"
            },
            "BlendFunc": {
              "Src": 1,
              "Dst": 771
            },
            "AnchorPoint": {
              "ScaleX": 0.5,
              "ScaleY": 0.5
            },
            "Position": {
              "X": 1227.2234,
              "Y": 1550.3989
            },
            "Scale": {
              "ScaleX": 1.0341,
              "ScaleY": 1.0
            },
            "CColor": {},
            "IconVisible": false,
            "PrePosition": {
              "X": 0.4794,
              "Y": 0.8613
            },
            "PreSize": {
              "X": 0.2508,
              "Y": 0.2783
            },
            "LeftMargin": 906.2234,
            "RightMargin": 1011.7766,
            "TopMargin": -0.8989,
            "BottomMargin": 1299.8989,
            "Tag": 41,
            "ActionTag": -1637614865,
            "Size": {
              "X": 642.0,
              "Y": 501.0
            },
            "Name": "Sprite_21_0_0",
            "ctype": "SpriteObjectData"
          },
          {
            "FileData": {
              "Type": "MarkedSubImage",
              "Path": "Sungura_mjanja_Hare_the_trickster/2-08.png",
              "Plist": "Sungura_mjanja_Hare_the_trickster/Sungura_mjanja_Hare_the_trickster.plist"
            },
            "BlendFunc": {
              "Src": 1,
              "Dst": 771
            },
            "AnchorPoint": {
              "ScaleX": 0.5,
              "ScaleY": 0.5
            },
            "Position": {
              "X": 765.2918,
              "Y": 1465.3601
            },
            "Scale": {
              "ScaleX": 1.0341,
              "ScaleY": 1.0
            },
            "CColor": {},
            "IconVisible": false,
            "PrePosition": {
              "X": 0.2989,
              "Y": 0.8141
            },
            "PreSize": {
              "X": 0.2508,
              "Y": 0.2783
            },
            "LeftMargin": 444.2918,
            "RightMargin": 1473.7083,
            "TopMargin": 84.1399,
            "BottomMargin": 1214.8601,
            "Tag": 42,
            "ActionTag": -1687703577,
            "Size": {
              "X": 642.0,
              "Y": 501.0
            },
            "Name": "Sprite_21_0_1",
            "ctype": "SpriteObjectData"
          },
          {
            "FileData": {
              "Type": "MarkedSubImage",
              "Path": "Sungura_mjanja_Hare_the_trickster/2-08.png",
              "Plist": "Sungura_mjanja_Hare_the_trickster/Sungura_mjanja_Hare_the_trickster.plist"
            },
            "BlendFunc": {
              "Src": 1,
              "Dst": 771
            },
            "AnchorPoint": {
              "ScaleX": 0.5,
              "ScaleY": 0.5
            },
            "Position": {
              "X": 154.0024,
              "Y": 1544.1917
            },
            "Scale": {
              "ScaleX": 1.0341,
              "ScaleY": 1.0
            },
            "CColor": {},
            "IconVisible": false,
            "PrePosition": {
              "X": 0.0602,
              "Y": 0.8579
            },
            "PreSize": {
              "X": 0.2508,
              "Y": 0.2783
            },
            "LeftMargin": -166.9976,
            "RightMargin": 2084.9976,
            "TopMargin": 5.3083,
            "BottomMargin": 1293.6917,
            "Tag": 43,
            "ActionTag": -516512990,
            "Size": {
              "X": 642.0,
              "Y": 501.0
            },
            "Name": "Sprite_21_0_2",
            "ctype": "SpriteObjectData"
          },
          {
            "FileData": {
              "Type": "MarkedSubImage",
              "Path": "Sungura_mjanja_Hare_the_trickster/2-07.png",
              "Plist": "Sungura_mjanja_Hare_the_trickster/Sungura_mjanja_Hare_the_trickster.plist"
            },
            "BlendFunc": {
              "Src": 1,
              "Dst": 771
            },
            "AnchorPoint": {
              "ScaleX": 0.5,
              "ScaleY": 0.5
            },
            "Position": {
              "X": 51.9693,
              "Y": 1734.2705
            },
            "Scale": {
              "ScaleX": 1.0,
              "ScaleY": 1.0
            },
            "CColor": {},
            "IconVisible": false,
            "PrePosition": {
              "X": 0.0203,
              "Y": 0.9635
            },
            "PreSize": {
              "X": 0.2824,
              "Y": 0.3233
            },
            "LeftMargin": -309.5307,
            "RightMargin": 2146.5308,
            "TopMargin": -225.2705,
            "BottomMargin": 1443.2705,
            "Tag": 44,
            "ActionTag": -413681980,
            "Size": {
              "X": 723.0,
              "Y": 582.0
            },
            "Name": "Sprite_20_0",
            "ctype": "SpriteObjectData"
          },
          {
            "FileData": {
              "Type": "MarkedSubImage",
              "Path": "Sungura_mjanja_Hare_the_trickster/2-07.png",
              "Plist": "Sungura_mjanja_Hare_the_trickster/Sungura_mjanja_Hare_the_trickster.plist"
            },
            "BlendFunc": {
              "Src": 1,
              "Dst": 771
            },
            "AnchorPoint": {
              "ScaleX": 0.5,
              "ScaleY": 0.5
            },
            "Position": {
              "X": 626.9213,
              "Y": 1684.8564
            },
            "Scale": {
              "ScaleX": 1.0,
              "ScaleY": 1.0
            },
            "CColor": {},
            "IconVisible": false,
            "PrePosition": {
              "X": 0.2449,
              "Y": 0.936
            },
            "PreSize": {
              "X": 0.2824,
              "Y": 0.3233
            },
            "LeftMargin": 265.4213,
            "RightMargin": 1571.5786,
            "TopMargin": -175.8564,
            "BottomMargin": 1393.8564,
            "Tag": 46,
            "ActionTag": -1672708763,
            "Size": {
              "X": 723.0,
              "Y": 582.0
            },
            "Name": "Sprite_20_0_0",
            "ctype": "SpriteObjectData"
          },
          {
            "FileData": {
              "Type": "MarkedSubImage",
              "Path": "Sungura_mjanja_Hare_the_trickster/2-07.png",
              "Plist": "Sungura_mjanja_Hare_the_trickster/Sungura_mjanja_Hare_the_trickster.plist"
            },
            "BlendFunc": {
              "Src": 1,
              "Dst": 771
            },
            "AnchorPoint": {
              "ScaleX": 0.5,
              "ScaleY": 0.5
            },
            "Position": {
              "X": 1191.8682,
              "Y": 1606.0271
            },
            "Scale": {
              "ScaleX": 1.0,
              "ScaleY": 1.0
            },
            "CColor": {},
            "IconVisible": false,
            "PrePosition": {
              "X": 0.4656,
              "Y": 0.8922
            },
            "PreSize": {
              "X": 0.2824,
              "Y": 0.3233
            },
            "LeftMargin": 830.3682,
            "RightMargin": 1006.6318,
            "TopMargin": -97.0271,
            "BottomMargin": 1315.0271,
            "Tag": 47,
            "ActionTag": -2102719016,
            "Size": {
              "X": 723.0,
              "Y": 582.0
            },
            "Name": "Sprite_20_0_1",
            "ctype": "SpriteObjectData"
          },
          {
            "FileData": {
              "Type": "MarkedSubImage",
              "Path": "Sungura_mjanja_Hare_the_trickster/2-07.png",
              "Plist": "Sungura_mjanja_Hare_the_trickster/Sungura_mjanja_Hare_the_trickster.plist"
            },
            "BlendFunc": {
              "Src": 1,
              "Dst": 771
            },
            "AnchorPoint": {
              "ScaleX": 0.5,
              "ScaleY": 0.5
            },
            "Position": {
              "X": 1783.0977,
              "Y": 1711.1345
            },
            "Scale": {
              "ScaleX": 1.0,
              "ScaleY": 1.0
            },
            "CColor": {},
            "IconVisible": false,
            "PrePosition": {
              "X": 0.6965,
              "Y": 0.9506
            },
            "PreSize": {
              "X": 0.2824,
              "Y": 0.3233
            },
            "LeftMargin": 1421.5977,
            "RightMargin": 415.4023,
            "TopMargin": -202.1345,
            "BottomMargin": 1420.1345,
            "Tag": 48,
            "ActionTag": 151946196,
            "Size": {
              "X": 723.0,
              "Y": 582.0
            },
            "Name": "Sprite_20_0_2",
            "ctype": "SpriteObjectData"
          },
          {
            "FileData": {
              "Type": "MarkedSubImage",
              "Path": "Sungura_mjanja_Hare_the_trickster/2-07.png",
              "Plist": "Sungura_mjanja_Hare_the_trickster/Sungura_mjanja_Hare_the_trickster.plist"
            },
            "BlendFunc": {
              "Src": 1,
              "Dst": 771
            },
            "AnchorPoint": {
              "ScaleX": 0.5,
              "ScaleY": 0.5
            },
            "Position": {
              "X": 2374.3215,
              "Y": 1619.1655
            },
            "Scale": {
              "ScaleX": 1.0,
              "ScaleY": 1.0
            },
            "CColor": {},
            "IconVisible": false,
            "PrePosition": {
              "X": 0.9275,
              "Y": 0.8995
            },
            "PreSize": {
              "X": 0.2824,
              "Y": 0.3233
            },
            "LeftMargin": 2012.8215,
            "RightMargin": -175.8215,
            "TopMargin": -110.1655,
            "BottomMargin": 1328.1655,
            "Tag": 49,
            "ActionTag": 883044619,
            "Size": {
              "X": 723.0,
              "Y": 582.0
            },
            "Name": "Sprite_20_0_3",
            "ctype": "SpriteObjectData"
          },
          {
            "FileData": {
              "Type": "MarkedSubImage",
              "Path": "Sungura_mjanja_Hare_the_trickster/2-06.png",
              "Plist": "Sungura_mjanja_Hare_the_trickster/Sungura_mjanja_Hare_the_trickster.plist"
            },
            "BlendFunc": {
              "Src": 1,
              "Dst": 771
            },
            "AnchorPoint": {
              "ScaleX": 0.5,
              "ScaleY": 0.5
            },
            "Position": {
              "X": 127.4625,
              "Y": 1640.1799
            },
            "Scale": {
              "ScaleX": 1.0,
              "ScaleY": 1.0
            },
            "CColor": {},
            "IconVisible": false,
            "PrePosition": {
              "X": 0.0498,
              "Y": 0.9112
            },
            "PreSize": {
              "X": 0.1934,
              "Y": 0.2256
            },
            "LeftMargin": -120.0375,
            "RightMargin": 2185.0376,
            "TopMargin": -43.1799,
            "BottomMargin": 1437.1799,
            "Tag": 37,
            "ActionTag": 104899481,
            "Size": {
              "X": 495.0,
              "Y": 406.0
            },
            "Name": "Sprite_19",
            "ctype": "SpriteObjectData"
          },
          {
            "FileData": {
              "Type": "MarkedSubImage",
              "Path": "Sungura_mjanja_Hare_the_trickster/2-06.png",
              "Plist": "Sungura_mjanja_Hare_the_trickster/Sungura_mjanja_Hare_the_trickster.plist"
            },
            "BlendFunc": {
              "Src": 1,
              "Dst": 771
            },
            "AnchorPoint": {
              "ScaleX": 0.5,
              "ScaleY": 0.5
            },
            "Position": {
              "X": 729.8835,
              "Y": 1558.9592
            },
            "Scale": {
              "ScaleX": 1.0,
              "ScaleY": 1.0
            },
            "CColor": {},
            "IconVisible": false,
            "PrePosition": {
              "X": 0.2851,
              "Y": 0.8661
            },
            "PreSize": {
              "X": 0.1934,
              "Y": 0.2256
            },
            "LeftMargin": 482.3835,
            "RightMargin": 1582.6165,
            "TopMargin": 38.0408,
            "BottomMargin": 1355.9592,
            "Tag": 50,
            "ActionTag": -1279852446,
            "Size": {
              "X": 495.0,
              "Y": 406.0
            },
            "Name": "Sprite_19_0",
            "ctype": "SpriteObjectData"
          },
          {
            "FileData": {
              "Type": "MarkedSubImage",
              "Path": "Sungura_mjanja_Hare_the_trickster/2-06.png",
              "Plist": "Sungura_mjanja_Hare_the_trickster/Sungura_mjanja_Hare_the_trickster.plist"
            },
            "BlendFunc": {
              "Src": 1,
              "Dst": 771
            },
            "AnchorPoint": {
              "ScaleX": 0.5,
              "ScaleY": 0.5
            },
            "Position": {
              "X": 1487.4041,
              "Y": 1601.3323
            },
            "Scale": {
              "ScaleX": 1.0,
              "ScaleY": 1.0
            },
            "CColor": {},
            "IconVisible": false,
            "PrePosition": {
              "X": 0.581,
              "Y": 0.8896
            },
            "PreSize": {
              "X": 0.1934,
              "Y": 0.2256
            },
            "LeftMargin": 1239.9041,
            "RightMargin": 825.0959,
            "TopMargin": -4.3323,
            "BottomMargin": 1398.3323,
            "Tag": 51,
            "ActionTag": -1192212441,
            "Size": {
              "X": 495.0,
              "Y": 406.0
            },
            "Name": "Sprite_19_1",
            "ctype": "SpriteObjectData"
          },
          {
            "FileData": {
              "Type": "MarkedSubImage",
              "Path": "Sungura_mjanja_Hare_the_trickster/2-06.png",
              "Plist": "Sungura_mjanja_Hare_the_trickster/Sungura_mjanja_Hare_the_trickster.plist"
            },
            "BlendFunc": {
              "Src": 1,
              "Dst": 771
            },
            "AnchorPoint": {
              "ScaleX": 0.5,
              "ScaleY": 0.5
            },
            "Position": {
              "X": 2213.7778,
              "Y": 1601.3323
            },
            "Scale": {
              "ScaleX": 1.0,
              "ScaleY": 1.0
            },
            "CColor": {},
            "IconVisible": false,
            "PrePosition": {
              "X": 0.8648,
              "Y": 0.8896
            },
            "PreSize": {
              "X": 0.1934,
              "Y": 0.2256
            },
            "LeftMargin": 1966.2778,
            "RightMargin": 98.7222,
            "TopMargin": -4.3323,
            "BottomMargin": 1398.3323,
            "Tag": 52,
            "ActionTag": -15869098,
            "Size": {
              "X": 495.0,
              "Y": 406.0
            },
            "Name": "Sprite_19_2",
            "ctype": "SpriteObjectData"
          },
          {
            "FileData": {
              "Type": "Normal",
              "Path": "Sungura_mjanja_Hare_the_trickster/elephant.json",
              "Plist": ""
            },
            "StretchWidthEnable": false,
            "StretchHeightEnable": false,
            "InnerActionSpeed": 1.0,
            "AnchorPoint": {},
            "Position": {
              "X": -244.2826,
              "Y": 96.5065
            },
            "Scale": {
              "ScaleX": -1.0,
              "ScaleY": 1.0
            },
            "CColor": {},
            "IconVisible": true,
            "PrePosition": {
              "X": -0.0954,
              "Y": 0.0536
            },
            "PreSize": {
              "X": 0.0,
              "Y": 0.0
            },
            "LeftMargin": -244.2826,
            "RightMargin": 2804.2827,
            "TopMargin": 1703.4935,
            "BottomMargin": 96.5065,
            "Tag": 56,
            "ActionTag": -998079649,
            "Size": {
              "X": 0.0,
              "Y": 0.0
            },
            "Name": "elephant",
            "ctype": "ProjectNodeObjectData"
          },
          {
            "FileData": {
              "Type": "MarkedSubImage",
              "Path": "Sungura_mjanja_Hare_the_trickster/pot.png",
              "Plist": "Sungura_mjanja_Hare_the_trickster/Sungura_mjanja_Hare_the_trickster.plist"
            },
            "BlendFunc": {
              "Src": 1,
              "Dst": 771
            },
            "AnchorPoint": {
              "ScaleX": 0.5,
              "ScaleY": 0.5
            },
            "Position": {
              "X": -202.2006,
              "Y": 845.8993
            },
            "Scale": {
              "ScaleX": 0.6943,
              "ScaleY": 0.6943
            },
            "CColor": {},
            "IconVisible": false,
            "PrePosition": {
              "X": -0.079,
              "Y": 0.4699
            },
            "PreSize": {
              "X": 0.1125,
              "Y": 0.1783
            },
            "LeftMargin": -346.2006,
            "RightMargin": 2618.2007,
            "TopMargin": 793.6007,
            "BottomMargin": 685.3993,
            "Tag": 110,
            "ActionTag": -582220063,
            "Size": {
              "X": 288.0,
              "Y": 321.0
            },
            "Name": "pot_50",
            "ctype": "SpriteObjectData"
          },
          {
            "FileData": {
              "Type": "MarkedSubImage",
              "Path": "Sungura_mjanja_Hare_the_trickster/2-02.png",
              "Plist": "Sungura_mjanja_Hare_the_trickster/Sungura_mjanja_Hare_the_trickster.plist"
            },
            "BlendFunc": {
              "Src": 1,
              "Dst": 771
            },
            "AnchorPoint": {
              "ScaleX": 0.5,
              "ScaleY": 0.5
            },
            "Position": {
              "X": 4995.8901,
              "Y": 936.7469
            },
            "Scale": {
              "ScaleX": 1.0,
              "ScaleY": 1.0
            },
            "CColor": {},
            "IconVisible": false,
            "PrePosition": {
              "X": 1.9515,
              "Y": 0.5204
            },
            "PreSize": {
              "X": 0.0582,
              "Y": 0.5883
            },
            "LeftMargin": 4921.3901,
            "RightMargin": -2510.3901,
            "TopMargin": 333.7532,
            "BottomMargin": 407.2469,
            "Tag": 431,
            "ActionTag": -2076227950,
            "Size": {
              "X": 149.0,
              "Y": 1059.0
            },
            "Name": "Sprite_15_1_0",
            "ctype": "SpriteObjectData"
          },
          {
            "FileData": {
              "Type": "MarkedSubImage",
              "Path": "Sungura_mjanja_Hare_the_trickster/2-02.png",
              "Plist": "Sungura_mjanja_Hare_the_trickster/Sungura_mjanja_Hare_the_trickster.plist"
            },
            "BlendFunc": {
              "Src": 1,
              "Dst": 771
            },
            "AnchorPoint": {
              "ScaleX": 0.5,
              "ScaleY": 0.5
            },
            "Position": {
              "X": 4255.6069,
              "Y": 906.75
            },
            "Scale": {
              "ScaleX": 1.0,
              "ScaleY": 1.0
            },
            "CColor": {},
            "IconVisible": false,
            "PrePosition": {
              "X": 1.6623,
              "Y": 0.5038
            },
            "PreSize": {
              "X": 0.0582,
              "Y": 0.5883
            },
            "LeftMargin": 4181.1069,
            "RightMargin": -1770.1069,
            "TopMargin": 363.75,
            "BottomMargin": 377.25,
            "Tag": 432,
            "ActionTag": -91299094,
            "Size": {
              "X": 149.0,
              "Y": 1059.0
            },
            "Name": "Sprite_15_0_0",
            "ctype": "SpriteObjectData"
          },
          {
            "FileData": {
              "Type": "MarkedSubImage",
              "Path": "Sungura_mjanja_Hare_the_trickster/2-02.png",
              "Plist": "Sungura_mjanja_Hare_the_trickster/Sungura_mjanja_Hare_the_trickster.plist"
            },
            "BlendFunc": {
              "Src": 1,
              "Dst": 771
            },
            "AnchorPoint": {
              "ScaleX": 0.5,
              "ScaleY": 0.5
            },
            "Position": {
              "X": 5425.5854,
              "Y": 836.7534
            },
            "Scale": {
              "ScaleX": 1.0,
              "ScaleY": 1.0
            },
            "CColor": {},
            "IconVisible": false,
            "PrePosition": {
              "X": 2.1194,
              "Y": 0.4649
            },
            "PreSize": {
              "X": 0.0582,
              "Y": 0.5883
            },
            "LeftMargin": 5351.0854,
            "RightMargin": -2940.0854,
            "TopMargin": 433.7466,
            "BottomMargin": 307.2534,
            "Tag": 433,
            "ActionTag": -266901448,
            "Size": {
              "X": 149.0,
              "Y": 1059.0
            },
            "Name": "Sprite_15_2",
            "ctype": "SpriteObjectData"
          },
          {
            "FileData": {
              "Type": "MarkedSubImage",
              "Path": "Sungura_mjanja_Hare_the_trickster/2-03.png",
              "Plist": "Sungura_mjanja_Hare_the_trickster/Sungura_mjanja_Hare_the_trickster.plist"
            },
            "BlendFunc": {
              "Src": 1,
              "Dst": 771
            },
            "AnchorPoint": {
              "ScaleX": 0.5,
              "ScaleY": 0.5
            },
            "Position": {
              "X": 4545.9048,
              "Y": 846.7518
            },
            "Scale": {
              "ScaleX": 1.0,
              "ScaleY": 1.0
            },
            "CColor": {},
            "IconVisible": false,
            "PrePosition": {
              "X": 1.7757,
              "Y": 0.4704
            },
            "PreSize": {
              "X": 0.0582,
              "Y": 0.5578
            },
            "LeftMargin": 4471.4048,
            "RightMargin": -2060.4048,
            "TopMargin": 451.2483,
            "BottomMargin": 344.7518,
            "Tag": 434,
            "ActionTag": 1983037331,
            "Size": {
              "X": 149.0,
              "Y": 1004.0
            },
            "Name": "Sprite_16_0",
            "ctype": "SpriteObjectData"
          },
          {
            "FileData": {
              "Type": "MarkedSubImage",
              "Path": "Sungura_mjanja_Hare_the_trickster/2-04.png",
              "Plist": "Sungura_mjanja_Hare_the_trickster/Sungura_mjanja_Hare_the_trickster.plist"
            },
            "BlendFunc": {
              "Src": 1,
              "Dst": 771
            },
            "AnchorPoint": {
              "ScaleX": 0.5,
              "ScaleY": 0.5
            },
            "Position": {
              "X": 3911.5225,
              "Y": 830.2684
            },
            "Scale": {
              "ScaleX": 1.0,
              "ScaleY": 1.0
            },
            "CColor": {},
            "IconVisible": false,
            "PrePosition": {
              "X": 1.5279,
              "Y": 0.4613
            },
            "PreSize": {
              "X": 0.2387,
              "Y": 0.5833
            },
            "LeftMargin": 3606.0225,
            "RightMargin": -1657.0225,
            "TopMargin": 444.7317,
            "BottomMargin": 305.2684,
            "Tag": 435,
            "ActionTag": -21325491,
            "Size": {
              "X": 611.0,
              "Y": 1050.0
            },
            "Name": "Sprite_17_0",
            "ctype": "SpriteObjectData"
          },
          {
            "FileData": {
              "Type": "MarkedSubImage",
              "Path": "Sungura_mjanja_Hare_the_trickster/2-08.png",
              "Plist": "Sungura_mjanja_Hare_the_trickster/Sungura_mjanja_Hare_the_trickster.plist"
            },
            "BlendFunc": {
              "Src": 1,
              "Dst": 771
            },
            "AnchorPoint": {
              "ScaleX": 0.5,
              "ScaleY": 0.5
            },
            "Position": {
              "X": 5279.7612,
              "Y": 1447.5432
            },
            "Scale": {
              "ScaleX": 1.0341,
              "ScaleY": 1.0
            },
            "CColor": {},
            "IconVisible": false,
            "PrePosition": {
              "X": 2.0624,
              "Y": 0.8042
            },
            "PreSize": {
              "X": 0.2508,
              "Y": 0.2783
            },
            "LeftMargin": 4958.7612,
            "RightMargin": -3040.7612,
            "TopMargin": 101.9568,
            "BottomMargin": 1197.0432,
            "Tag": 436,
            "ActionTag": -1306158871,
            "Size": {
              "X": 642.0,
              "Y": 501.0
            },
            "Name": "Sprite_21_1",
            "ctype": "SpriteObjectData"
          },
          {
            "FileData": {
              "Type": "MarkedSubImage",
              "Path": "Sungura_mjanja_Hare_the_trickster/2-08.png",
              "Plist": "Sungura_mjanja_Hare_the_trickster/Sungura_mjanja_Hare_the_trickster.plist"
            },
            "BlendFunc": {
              "Src": 1,
              "Dst": 771
            },
            "AnchorPoint": {
              "ScaleX": 0.5,
              "ScaleY": 0.5
            },
            "Position": {
              "X": 4733.0859,
              "Y": 1463.8184
            },
            "Scale": {
              "ScaleX": 1.0341,
              "ScaleY": 1.0
            },
            "CColor": {},
            "IconVisible": false,
            "PrePosition": {
              "X": 1.8489,
              "Y": 0.8132
            },
            "PreSize": {
              "X": 0.2508,
              "Y": 0.2783
            },
            "LeftMargin": 4412.0859,
            "RightMargin": -2494.0859,
            "TopMargin": 85.6816,
            "BottomMargin": 1213.3184,
            "Tag": 437,
            "ActionTag": -1406668354,
            "Size": {
              "X": 642.0,
              "Y": 501.0
            },
            "Name": "Sprite_21_0_3",
            "ctype": "SpriteObjectData"
          },
          {
            "FileData": {
              "Type": "MarkedSubImage",
              "Path": "Sungura_mjanja_Hare_the_trickster/2-08.png",
              "Plist": "Sungura_mjanja_Hare_the_trickster/Sungura_mjanja_Hare_the_trickster.plist"
            },
            "BlendFunc": {
              "Src": 1,
              "Dst": 771
            },
            "AnchorPoint": {
              "ScaleX": 0.5,
              "ScaleY": 0.5
            },
            "Position": {
              "X": 4227.1772,
              "Y": 1460.387
            },
            "Scale": {
              "ScaleX": 1.0341,
              "ScaleY": 1.0
            },
            "CColor": {},
            "IconVisible": false,
            "PrePosition": {
              "X": 1.6512,
              "Y": 0.8113
            },
            "PreSize": {
              "X": 0.2508,
              "Y": 0.2783
            },
            "LeftMargin": 3906.1772,
            "RightMargin": -1988.1772,
            "TopMargin": 89.113,
            "BottomMargin": 1209.887,
            "Tag": 438,
            "ActionTag": 474636400,
            "Size": {
              "X": 642.0,
              "Y": 501.0
            },
            "Name": "Sprite_21_0_0_0",
            "ctype": "SpriteObjectData"
          },
          {
            "FileData": {
              "Type": "MarkedSubImage",
              "Path": "Sungura_mjanja_Hare_the_trickster/2-08.png",
              "Plist": "Sungura_mjanja_Hare_the_trickster/Sungura_mjanja_Hare_the_trickster.plist"
            },
            "BlendFunc": {
              "Src": 1,
              "Dst": 771
            },
            "AnchorPoint": {
              "ScaleX": 0.5,
              "ScaleY": 0.5
            },
            "Position": {
              "X": 3765.2524,
              "Y": 1375.355
            },
            "Scale": {
              "ScaleX": 1.0341,
              "ScaleY": 1.0
            },
            "CColor": {},
            "IconVisible": false,
            "PrePosition": {
              "X": 1.4708,
              "Y": 0.7641
            },
            "PreSize": {
              "X": 0.2508,
              "Y": 0.2783
            },
            "LeftMargin": 3444.2524,
            "RightMargin": -1526.2524,
            "TopMargin": 174.145,
            "BottomMargin": 1124.855,
            "Tag": 439,
            "ActionTag": -467463433,
            "Size": {
              "X": 642.0,
              "Y": 501.0
            },
            "Name": "Sprite_21_0_1_0",
            "ctype": "SpriteObjectData"
          },
          {
            "FileData": {
              "Type": "MarkedSubImage",
              "Path": "Sungura_mjanja_Hare_the_trickster/2-07.png",
              "Plist": "Sungura_mjanja_Hare_the_trickster/Sungura_mjanja_Hare_the_trickster.plist"
            },
            "BlendFunc": {
              "Src": 1,
              "Dst": 771
            },
            "AnchorPoint": {
              "ScaleX": 0.5,
              "ScaleY": 0.5
            },
            "Position": {
              "X": 3626.8955,
              "Y": 1594.843
            },
            "Scale": {
              "ScaleX": 1.0,
              "ScaleY": 1.0
            },
            "CColor": {},
            "IconVisible": false,
            "PrePosition": {
              "X": 1.4168,
              "Y": 0.886
            },
            "PreSize": {
              "X": 0.2824,
              "Y": 0.3233
            },
            "LeftMargin": 3265.3955,
            "RightMargin": -1428.3955,
            "TopMargin": -85.843,
            "BottomMargin": 1303.843,
            "Tag": 442,
            "ActionTag": -828869116,
            "Size": {
              "X": 723.0,
              "Y": 582.0
            },
            "Name": "Sprite_20_0_0_0",
            "ctype": "SpriteObjectData"
          },
          {
            "FileData": {
              "Type": "MarkedSubImage",
              "Path": "Sungura_mjanja_Hare_the_trickster/2-07.png",
              "Plist": "Sungura_mjanja_Hare_the_trickster/Sungura_mjanja_Hare_the_trickster.plist"
            },
            "BlendFunc": {
              "Src": 1,
              "Dst": 771
            },
            "AnchorPoint": {
              "ScaleX": 0.5,
              "ScaleY": 0.5
            },
            "Position": {
              "X": 4191.8545,
              "Y": 1516.0186
            },
            "Scale": {
              "ScaleX": 1.0,
              "ScaleY": 1.0
            },
            "CColor": {},
            "IconVisible": false,
            "PrePosition": {
              "X": 1.6374,
              "Y": 0.8422
            },
            "PreSize": {
              "X": 0.2824,
              "Y": 0.3233
            },
            "LeftMargin": 3830.3545,
            "RightMargin": -1993.3545,
            "TopMargin": -7.0186,
            "BottomMargin": 1225.0186,
            "Tag": 443,
            "ActionTag": -1778102008,
            "Size": {
              "X": 723.0,
              "Y": 582.0
            },
            "Name": "Sprite_20_0_1_0",
            "ctype": "SpriteObjectData"
          },
          {
            "FileData": {
              "Type": "MarkedSubImage",
              "Path": "Sungura_mjanja_Hare_the_trickster/2-07.png",
              "Plist": "Sungura_mjanja_Hare_the_trickster/Sungura_mjanja_Hare_the_trickster.plist"
            },
            "BlendFunc": {
              "Src": 1,
              "Dst": 771
            },
            "AnchorPoint": {
              "ScaleX": 0.5,
              "ScaleY": 0.5
            },
            "Position": {
              "X": 4783.0923,
              "Y": 1621.1187
            },
            "Scale": {
              "ScaleX": 1.0,
              "ScaleY": 1.0
            },
            "CColor": {},
            "IconVisible": false,
            "PrePosition": {
              "X": 1.8684,
              "Y": 0.9006
            },
            "PreSize": {
              "X": 0.2824,
              "Y": 0.3233
            },
            "LeftMargin": 4421.5923,
            "RightMargin": -2584.5923,
            "TopMargin": -112.1187,
            "BottomMargin": 1330.1187,
            "Tag": 444,
            "ActionTag": -550151510,
            "Size": {
              "X": 723.0,
              "Y": 582.0
            },
            "Name": "Sprite_20_0_2_0",
            "ctype": "SpriteObjectData"
          },
          {
            "FileData": {
              "Type": "MarkedSubImage",
              "Path": "Sungura_mjanja_Hare_the_trickster/2-07.png",
              "Plist": "Sungura_mjanja_Hare_the_trickster/Sungura_mjanja_Hare_the_trickster.plist"
            },
            "BlendFunc": {
              "Src": 1,
              "Dst": 771
            },
            "AnchorPoint": {
              "ScaleX": 0.5,
              "ScaleY": 0.5
            },
            "Position": {
              "X": 5374.3086,
              "Y": 1529.157
            },
            "Scale": {
              "ScaleX": 1.0,
              "ScaleY": 1.0
            },
            "CColor": {},
            "IconVisible": false,
            "PrePosition": {
              "X": 2.0993,
              "Y": 0.8495
            },
            "PreSize": {
              "X": 0.2824,
              "Y": 0.3233
            },
            "LeftMargin": 5012.8086,
            "RightMargin": -3175.8086,
            "TopMargin": -20.157,
            "BottomMargin": 1238.157,
            "Tag": 445,
            "ActionTag": -905981365,
            "Size": {
              "X": 723.0,
              "Y": 582.0
            },
            "Name": "Sprite_20_0_3_0",
            "ctype": "SpriteObjectData"
          },
          {
            "FileData": {
              "Type": "MarkedSubImage",
              "Path": "Sungura_mjanja_Hare_the_trickster/2-06.png",
              "Plist": "Sungura_mjanja_Hare_the_trickster/Sungura_mjanja_Hare_the_trickster.plist"
            },
            "BlendFunc": {
              "Src": 1,
              "Dst": 771
            },
            "AnchorPoint": {
              "ScaleX": 0.5,
              "ScaleY": 0.5
            },
            "Position": {
              "X": 3729.8398,
              "Y": 1468.9465
            },
            "Scale": {
              "ScaleX": 1.0,
              "ScaleY": 1.0
            },
            "CColor": {},
            "IconVisible": false,
            "PrePosition": {
              "X": 1.457,
              "Y": 0.8161
            },
            "PreSize": {
              "X": 0.1934,
              "Y": 0.2256
            },
            "LeftMargin": 3482.3398,
            "RightMargin": -1417.3398,
            "TopMargin": 128.0535,
            "BottomMargin": 1265.9465,
            "Tag": 447,
            "ActionTag": 569461126,
            "Size": {
              "X": 495.0,
              "Y": 406.0
            },
            "Name": "Sprite_19_0_0",
            "ctype": "SpriteObjectData"
          },
          {
            "FileData": {
              "Type": "MarkedSubImage",
              "Path": "Sungura_mjanja_Hare_the_trickster/2-06.png",
              "Plist": "Sungura_mjanja_Hare_the_trickster/Sungura_mjanja_Hare_the_trickster.plist"
            },
            "BlendFunc": {
              "Src": 1,
              "Dst": 771
            },
            "AnchorPoint": {
              "ScaleX": 0.5,
              "ScaleY": 0.5
            },
            "Position": {
              "X": 4487.3677,
              "Y": 1511.3157
            },
            "Scale": {
              "ScaleX": 1.0,
              "ScaleY": 1.0
            },
            "CColor": {},
            "IconVisible": false,
            "PrePosition": {
              "X": 1.7529,
              "Y": 0.8396
            },
            "PreSize": {
              "X": 0.1934,
              "Y": 0.2256
            },
            "LeftMargin": 4239.8677,
            "RightMargin": -2174.8677,
            "TopMargin": 85.6843,
            "BottomMargin": 1308.3157,
            "Tag": 448,
            "ActionTag": 1364796223,
            "Size": {
              "X": 495.0,
              "Y": 406.0
            },
            "Name": "Sprite_19_1_0",
            "ctype": "SpriteObjectData"
          },
          {
            "FileData": {
              "Type": "MarkedSubImage",
              "Path": "Sungura_mjanja_Hare_the_trickster/2-06.png",
              "Plist": "Sungura_mjanja_Hare_the_trickster/Sungura_mjanja_Hare_the_trickster.plist"
            },
            "BlendFunc": {
              "Src": 1,
              "Dst": 771
            },
            "AnchorPoint": {
              "ScaleX": 0.5,
              "ScaleY": 0.5
            },
            "Position": {
              "X": 5213.7324,
              "Y": 1511.3157
            },
            "Scale": {
              "ScaleX": 1.0,
              "ScaleY": 1.0
            },
            "CColor": {},
            "IconVisible": false,
            "PrePosition": {
              "X": 2.0366,
              "Y": 0.8396
            },
            "PreSize": {
              "X": 0.1934,
              "Y": 0.2256
            },
            "LeftMargin": 4966.2324,
            "RightMargin": -2901.2324,
            "TopMargin": 85.6843,
            "BottomMargin": 1308.3157,
            "Tag": 449,
            "ActionTag": 1649610432,
            "Size": {
              "X": 495.0,
              "Y": 406.0
            },
            "Name": "Sprite_19_2_0",
            "ctype": "SpriteObjectData"
          },
          {
            "FileData": {
              "Type": "Normal",
              "Path": "Sungura_mjanja_Hare_the_trickster/bird.json",
              "Plist": ""
            },
            "StretchWidthEnable": false,
            "StretchHeightEnable": false,
            "InnerActionSpeed": 1.0,
            "AnchorPoint": {},
            "Position": {
              "X": 3289.396,
              "Y": 1080.8489
            },
            "Scale": {
              "ScaleX": 1.0,
              "ScaleY": 1.0
            },
            "CColor": {},
            "IconVisible": true,
            "PrePosition": {
              "X": 1.2849,
              "Y": 0.6005
            },
            "PreSize": {
              "X": 0.0,
              "Y": 0.0
            },
            "LeftMargin": 3289.396,
            "RightMargin": -729.396,
            "TopMargin": 719.1511,
            "BottomMargin": 1080.8489,
            "Tag": 436,
            "ActionTag": 770026957,
            "Size": {
              "X": 0.0,
              "Y": 0.0
            },
            "Name": "bird ",
            "ctype": "ProjectNodeObjectData"
          },
          {
            "FileData": {
              "Type": "Normal",
              "Path": "Sungura_mjanja_Hare_the_trickster/rabit.json",
              "Plist": ""
            },
            "StretchWidthEnable": false,
            "StretchHeightEnable": false,
            "InnerActionSpeed": 1.0,
            "AnchorPoint": {},
            "Position": {
              "X": -326.9784,
              "Y": 766.5491
            },
            "Scale": {
              "ScaleX": -0.5438,
              "ScaleY": 0.5438
            },
            "CColor": {},
            "IconVisible": true,
            "PrePosition": {
              "X": -0.1277,
              "Y": 0.4259
            },
            "PreSize": {
              "X": 0.0,
              "Y": 0.0
            },
            "LeftMargin": -326.9784,
            "RightMargin": 2886.9783,
            "TopMargin": 1033.4509,
            "BottomMargin": 766.5491,
            "UserData": "hop;drag",
            "Tag": 655,
            "ActionTag": -2108197269,
            "Size": {
              "X": 0.0,
              "Y": 0.0
            },
            "Name": "rabit",
            "ctype": "ProjectNodeObjectData"
          }
        ],
        "Size": {
          "X": 2560.0,
          "Y": 1800.0
        },
        "Name": "Scene",
        "ctype": "SingleNodeObjectData"
      },
      "UsedResources": [
        "bird.json",
        "elephant.json",
        "rabit.json",
        "Sungura_mjanja_Hare_the_trickster.plist",
        "Sungura_mjanja_Hare_the_trickster.png"
      ],
      "ctype": "GameFileData"
    }
  },
  "Type": "Scene"
}