{
  "ID": "51ca6014-8d52-4273-a782-f59aa2ef7e57",
  "Version": "3.10.0.0",
  "Name": "Adun_the_beautiful_04",
  "Content": {
    "Content": {
      "Animation": {
        "Duration": 575,
        "Speed": 1.0,
        "ActivedAnimationName": "master",
        "Timelines": [
          {
            "ActionTag": -805711903,
            "Property": "Position",
            "Frames": [
              {
                "X": 1138.797,
                "Y": 1616.1449,
                "FrameIndex": 470,
                "EasingData": {
                  "Type": 0
                },
                "ctype": "PointFrameData"
              },
              {
                "X": 1682.8562,
                "Y": 1609.9277,
                "FrameIndex": 485,
                "EasingData": {
                  "Type": 0
                },
                "ctype": "PointFrameData"
              },
              {
                "X": 1138.797,
                "Y": 1616.1449,
                "FrameIndex": 500,
                "EasingData": {
                  "Type": 0
                },
                "ctype": "PointFrameData"
              },
              {
                "X": 691.3914,
                "Y": 1623.0098,
                "FrameIndex": 515,
                "EasingData": {
                  "Type": 0
                },
                "ctype": "PointFrameData"
              },
              {
                "X": 1138.797,
                "Y": 1616.1449,
                "FrameIndex": 530,
                "EasingData": {
                  "Type": 0
                },
                "ctype": "PointFrameData"
              }
            ],
            "ctype": "TimelineData"
          },
          {
            "ActionTag": -805711903,
            "Property": "Scale",
            "Frames": [
              {
                "X": 1.0,
                "Y": 1.0,
                "FrameIndex": 470,
                "EasingData": {
                  "Type": 0
                },
                "ctype": "ScaleValueFrameData"
              },
              {
                "X": 1.0,
                "Y": 1.0,
                "FrameIndex": 485,
                "EasingData": {
                  "Type": 0
                },
                "ctype": "ScaleValueFrameData"
              },
              {
                "X": 1.0,
                "Y": 1.0,
                "FrameIndex": 500,
                "EasingData": {
                  "Type": 0
                },
                "ctype": "ScaleValueFrameData"
              },
              {
                "X": 1.0,
                "Y": 1.0,
                "FrameIndex": 515,
                "EasingData": {
                  "Type": 0
                },
                "ctype": "ScaleValueFrameData"
              },
              {
                "X": 1.0,
                "Y": 1.0,
                "FrameIndex": 530,
                "EasingData": {
                  "Type": 0
                },
                "ctype": "ScaleValueFrameData"
              }
            ],
            "ctype": "TimelineData"
          },
          {
            "ActionTag": -805711903,
            "Property": "RotationSkew",
            "Frames": [
              {
                "X": 0.0,
                "Y": 0.0,
                "FrameIndex": 470,
                "EasingData": {
                  "Type": 0
                },
                "ctype": "ScaleValueFrameData"
              },
              {
                "X": 0.0,
                "Y": 0.0,
                "FrameIndex": 485,
                "EasingData": {
                  "Type": 0
                },
                "ctype": "ScaleValueFrameData"
              },
              {
                "X": 0.0,
                "Y": 0.0,
                "FrameIndex": 500,
                "EasingData": {
                  "Type": 0
                },
                "ctype": "ScaleValueFrameData"
              },
              {
                "X": 0.0,
                "Y": 0.0,
                "FrameIndex": 515,
                "EasingData": {
                  "Type": 0
                },
                "ctype": "ScaleValueFrameData"
              },
              {
                "X": 0.0,
                "Y": 0.0,
                "FrameIndex": 530,
                "EasingData": {
                  "Type": 0
                },
                "ctype": "ScaleValueFrameData"
              }
            ],
            "ctype": "TimelineData"
          },
          {
            "ActionTag": -1670027600,
            "Property": "Position",
            "Frames": [
              {
                "X": 558.5298,
                "Y": 762.2684,
                "FrameIndex": 535,
                "EasingData": {
                  "Type": 0
                },
                "ctype": "PointFrameData"
              },
              {
                "X": 558.5295,
                "Y": 762.2684,
                "FrameIndex": 555,
                "EasingData": {
                  "Type": 0
                },
                "ctype": "PointFrameData"
              },
              {
                "X": 558.5298,
                "Y": 762.2684,
                "FrameIndex": 575,
                "EasingData": {
                  "Type": 0
                },
                "ctype": "PointFrameData"
              }
            ],
            "ctype": "TimelineData"
          },
          {
            "ActionTag": -1670027600,
            "Property": "Scale",
            "Frames": [
              {
                "X": 1.5923,
                "Y": 1.5923,
                "FrameIndex": 535,
                "EasingData": {
                  "Type": 0
                },
                "ctype": "ScaleValueFrameData"
              },
              {
                "X": 1.9648,
                "Y": 1.9648,
                "FrameIndex": 555,
                "EasingData": {
                  "Type": 0
                },
                "ctype": "ScaleValueFrameData"
              },
              {
                "X": 1.5923,
                "Y": 1.5923,
                "FrameIndex": 575,
                "EasingData": {
                  "Type": 0
                },
                "ctype": "ScaleValueFrameData"
              }
            ],
            "ctype": "TimelineData"
          },
          {
            "ActionTag": -1670027600,
            "Property": "RotationSkew",
            "Frames": [
              {
                "X": 0.0,
                "Y": 0.0,
                "FrameIndex": 535,
                "EasingData": {
                  "Type": 0
                },
                "ctype": "ScaleValueFrameData"
              },
              {
                "X": 0.0,
                "Y": 0.0,
                "FrameIndex": 555,
                "EasingData": {
                  "Type": 0
                },
                "ctype": "ScaleValueFrameData"
              },
              {
                "X": 0.0,
                "Y": 0.0,
                "FrameIndex": 575,
                "EasingData": {
                  "Type": 0
                },
                "ctype": "ScaleValueFrameData"
              }
            ],
            "ctype": "TimelineData"
          },
          {
            "ActionTag": 291253660,
            "Property": "ActionValue",
            "Frames": [
              {
                "InnerActionType": "LoopAction",
                "CurrentAniamtionName": "walk",
                "SingleFrameIndex": 0,
                "FrameIndex": 0,
                "Tween": false,
                "ctype": "InnerActionFrameData"
              },
              {
                "InnerActionType": "LoopAction",
                "CurrentAniamtionName": "walk",
                "SingleFrameIndex": 0,
                "FrameIndex": 80,
                "Tween": false,
                "ctype": "InnerActionFrameData"
              },
              {
                "InnerActionType": "LoopAction",
                "CurrentAniamtionName": "walk",
                "SingleFrameIndex": 0,
                "FrameIndex": 160,
                "Tween": false,
                "ctype": "InnerActionFrameData"
              },
              {
                "InnerActionType": "LoopAction",
                "CurrentAniamtionName": "walk",
                "SingleFrameIndex": 0,
                "FrameIndex": 240,
                "Tween": false,
                "ctype": "InnerActionFrameData"
              },
              {
                "InnerActionType": "LoopAction",
                "CurrentAniamtionName": "walk",
                "SingleFrameIndex": 0,
                "FrameIndex": 320,
                "Tween": false,
                "ctype": "InnerActionFrameData"
              },
              {
                "InnerActionType": "LoopAction",
                "CurrentAniamtionName": "blink",
                "SingleFrameIndex": 0,
                "FrameIndex": 321,
                "Tween": false,
                "ctype": "InnerActionFrameData"
              },
              {
                "InnerActionType": "LoopAction",
                "CurrentAniamtionName": "blink",
                "SingleFrameIndex": 0,
                "FrameIndex": 400,
                "Tween": false,
                "ctype": "InnerActionFrameData"
              }
            ],
            "ctype": "TimelineData"
          },
          {
            "ActionTag": 291253660,
            "Property": "Position",
            "Frames": [
              {
                "X": 236.6998,
                "Y": 422.4302,
                "FrameIndex": 0,
                "EasingData": {
                  "Type": 0
                },
                "ctype": "PointFrameData"
              },
              {
                "X": 515.1379,
                "Y": 416.7474,
                "FrameIndex": 80,
                "EasingData": {
                  "Type": 0
                },
                "ctype": "PointFrameData"
              },
              {
                "X": 835.2474,
                "Y": 414.853,
                "FrameIndex": 160,
                "EasingData": {
                  "Type": 0
                },
                "ctype": "PointFrameData"
              },
              {
                "X": 1218.7329,
                "Y": 372.7271,
                "FrameIndex": 240,
                "EasingData": {
                  "Type": 0
                },
                "ctype": "PointFrameData"
              },
              {
                "X": 1703.8237,
                "Y": 338.0768,
                "FrameIndex": 320,
                "EasingData": {
                  "Type": 0
                },
                "ctype": "PointFrameData"
              },
              {
                "X": 1703.8237,
                "Y": 338.0768,
                "FrameIndex": 321,
                "EasingData": {
                  "Type": 0
                },
                "ctype": "PointFrameData"
              },
              {
                "X": 1703.8237,
                "Y": 338.0768,
                "FrameIndex": 400,
                "EasingData": {
                  "Type": 0
                },
                "ctype": "PointFrameData"
              }
            ],
            "ctype": "TimelineData"
          },
          {
            "ActionTag": 291253660,
            "Property": "Scale",
            "Frames": [
              {
                "X": -0.6345,
                "Y": 0.6345,
                "FrameIndex": 0,
                "EasingData": {
                  "Type": 0
                },
                "ctype": "ScaleValueFrameData"
              },
              {
                "X": -0.6345,
                "Y": 0.6345,
                "FrameIndex": 80,
                "EasingData": {
                  "Type": 0
                },
                "ctype": "ScaleValueFrameData"
              },
              {
                "X": -0.6345,
                "Y": 0.6345,
                "FrameIndex": 160,
                "EasingData": {
                  "Type": 0
                },
                "ctype": "ScaleValueFrameData"
              },
              {
                "X": -0.6345,
                "Y": 0.6345,
                "FrameIndex": 240,
                "EasingData": {
                  "Type": 0
                },
                "ctype": "ScaleValueFrameData"
              },
              {
                "X": -0.6345,
                "Y": 0.6345,
                "FrameIndex": 320,
                "EasingData": {
                  "Type": 0
                },
                "ctype": "ScaleValueFrameData"
              },
              {
                "X": -0.6345,
                "Y": 0.6345,
                "FrameIndex": 321,
                "EasingData": {
                  "Type": 0
                },
                "ctype": "ScaleValueFrameData"
              },
              {
                "X": -0.6345,
                "Y": 0.6345,
                "FrameIndex": 400,
                "EasingData": {
                  "Type": 0
                },
                "ctype": "ScaleValueFrameData"
              }
            ],
            "ctype": "TimelineData"
          },
          {
            "ActionTag": 291253660,
            "Property": "RotationSkew",
            "Frames": [
              {
                "X": 0.0,
                "Y": 0.0,
                "FrameIndex": 0,
                "EasingData": {
                  "Type": 0
                },
                "ctype": "ScaleValueFrameData"
              },
              {
                "X": 0.0,
                "Y": 0.0,
                "FrameIndex": 80,
                "EasingData": {
                  "Type": 0
                },
                "ctype": "ScaleValueFrameData"
              },
              {
                "X": 0.0,
                "Y": 0.0,
                "FrameIndex": 160,
                "EasingData": {
                  "Type": 0
                },
                "ctype": "ScaleValueFrameData"
              },
              {
                "X": 0.0,
                "Y": 0.0,
                "FrameIndex": 240,
                "EasingData": {
                  "Type": 0
                },
                "ctype": "ScaleValueFrameData"
              },
              {
                "X": 0.0,
                "Y": 0.0,
                "FrameIndex": 320,
                "EasingData": {
                  "Type": 0
                },
                "ctype": "ScaleValueFrameData"
              },
              {
                "X": 0.0,
                "Y": 0.0,
                "FrameIndex": 321,
                "EasingData": {
                  "Type": 0
                },
                "ctype": "ScaleValueFrameData"
              },
              {
                "X": 0.0,
                "Y": 0.0,
                "FrameIndex": 400,
                "EasingData": {
                  "Type": 0
                },
                "ctype": "ScaleValueFrameData"
              }
            ],
            "ctype": "TimelineData"
          },
          {
            "ActionTag": 291253660,
            "Property": "FrameEvent",
            "Frames": [
              {
                "Value": "walking",
                "FrameIndex": 0,
                "Tween": false,
                "ctype": "EventFrameData"
              },
              {
                "Value": "walking",
                "FrameIndex": 320,
                "Tween": false,
                "ctype": "EventFrameData"
              },
              {
                "Value": "",
                "FrameIndex": 321,
                "Tween": false,
                "ctype": "EventFrameData"
              },
              {
                "Value": "",
                "FrameIndex": 400,
                "Tween": false,
                "ctype": "EventFrameData"
              }
            ],
            "ctype": "TimelineData"
          },
          {
            "ActionTag": 1625798699,
            "Property": "Position",
            "Frames": [
              {
                "X": 1948.5369,
                "Y": 472.4778,
                "FrameIndex": 405,
                "EasingData": {
                  "Type": 0
                },
                "ctype": "PointFrameData"
              },
              {
                "X": 1948.5359,
                "Y": 472.4777,
                "FrameIndex": 420,
                "EasingData": {
                  "Type": 0
                },
                "ctype": "PointFrameData"
              },
              {
                "X": 1948.5369,
                "Y": 472.4778,
                "FrameIndex": 435,
                "EasingData": {
                  "Type": 0
                },
                "ctype": "PointFrameData"
              },
              {
                "X": 1948.5364,
                "Y": 472.4778,
                "FrameIndex": 450,
                "EasingData": {
                  "Type": 0
                },
                "ctype": "PointFrameData"
              },
              {
                "X": 1948.5369,
                "Y": 472.4778,
                "FrameIndex": 465,
                "EasingData": {
                  "Type": 0
                },
                "ctype": "PointFrameData"
              }
            ],
            "ctype": "TimelineData"
          },
          {
            "ActionTag": 1625798699,
            "Property": "Scale",
            "Frames": [
              {
                "X": 0.5064,
                "Y": 0.5064,
                "FrameIndex": 405,
                "EasingData": {
                  "Type": 0
                },
                "ctype": "ScaleValueFrameData"
              },
              {
                "X": 0.5064,
                "Y": 0.5064,
                "FrameIndex": 420,
                "EasingData": {
                  "Type": 0
                },
                "ctype": "ScaleValueFrameData"
              },
              {
                "X": 0.5064,
                "Y": 0.5064,
                "FrameIndex": 435,
                "EasingData": {
                  "Type": 0
                },
                "ctype": "ScaleValueFrameData"
              },
              {
                "X": 0.5064,
                "Y": 0.5064,
                "FrameIndex": 450,
                "EasingData": {
                  "Type": 0
                },
                "ctype": "ScaleValueFrameData"
              },
              {
                "X": 0.5064,
                "Y": 0.5064,
                "FrameIndex": 465,
                "EasingData": {
                  "Type": 0
                },
                "ctype": "ScaleValueFrameData"
              }
            ],
            "ctype": "TimelineData"
          },
          {
            "ActionTag": 1625798699,
            "Property": "RotationSkew",
            "Frames": [
              {
                "X": 0.0,
                "Y": 0.0,
                "FrameIndex": 405,
                "EasingData": {
                  "Type": 0
                },
                "ctype": "ScaleValueFrameData"
              },
              {
                "X": -7.6467,
                "Y": -7.6389,
                "FrameIndex": 420,
                "EasingData": {
                  "Type": 0
                },
                "ctype": "ScaleValueFrameData"
              },
              {
                "X": 0.0,
                "Y": 0.0,
                "FrameIndex": 435,
                "EasingData": {
                  "Type": 0
                },
                "ctype": "ScaleValueFrameData"
              },
              {
                "X": 6.1717,
                "Y": 6.1621,
                "FrameIndex": 450,
                "EasingData": {
                  "Type": 0
                },
                "ctype": "ScaleValueFrameData"
              },
              {
                "X": 0.0,
                "Y": 0.0,
                "FrameIndex": 465,
                "EasingData": {
                  "Type": 0
                },
                "ctype": "ScaleValueFrameData"
              }
            ],
            "ctype": "TimelineData"
          },
          {
            "ActionTag": -1797262533,
            "Property": "Position",
            "Frames": [
              {
                "X": 1336.1726,
                "Y": 453.986,
                "FrameIndex": 405,
                "EasingData": {
                  "Type": 0
                },
                "ctype": "PointFrameData"
              },
              {
                "X": 1336.1721,
                "Y": 453.9857,
                "FrameIndex": 420,
                "EasingData": {
                  "Type": 0
                },
                "ctype": "PointFrameData"
              },
              {
                "X": 1336.1726,
                "Y": 453.986,
                "FrameIndex": 435,
                "EasingData": {
                  "Type": 0
                },
                "ctype": "PointFrameData"
              },
              {
                "X": 1336.1724,
                "Y": 453.9858,
                "FrameIndex": 450,
                "EasingData": {
                  "Type": 0
                },
                "ctype": "PointFrameData"
              },
              {
                "X": 1336.1726,
                "Y": 453.986,
                "FrameIndex": 465,
                "EasingData": {
                  "Type": 0
                },
                "ctype": "PointFrameData"
              }
            ],
            "ctype": "TimelineData"
          },
          {
            "ActionTag": -1797262533,
            "Property": "Scale",
            "Frames": [
              {
                "X": 0.5064,
                "Y": 0.5064,
                "FrameIndex": 405,
                "EasingData": {
                  "Type": 0
                },
                "ctype": "ScaleValueFrameData"
              },
              {
                "X": 0.5064,
                "Y": 0.5064,
                "FrameIndex": 420,
                "EasingData": {
                  "Type": 0
                },
                "ctype": "ScaleValueFrameData"
              },
              {
                "X": 0.5064,
                "Y": 0.5064,
                "FrameIndex": 435,
                "EasingData": {
                  "Type": 0
                },
                "ctype": "ScaleValueFrameData"
              },
              {
                "X": 0.5064,
                "Y": 0.5064,
                "FrameIndex": 450,
                "EasingData": {
                  "Type": 0
                },
                "ctype": "ScaleValueFrameData"
              },
              {
                "X": 0.5064,
                "Y": 0.5064,
                "FrameIndex": 465,
                "EasingData": {
                  "Type": 0
                },
                "ctype": "ScaleValueFrameData"
              }
            ],
            "ctype": "TimelineData"
          },
          {
            "ActionTag": -1797262533,
            "Property": "RotationSkew",
            "Frames": [
              {
                "X": 0.0,
                "Y": 0.0,
                "FrameIndex": 405,
                "EasingData": {
                  "Type": 0
                },
                "ctype": "ScaleValueFrameData"
              },
              {
                "X": 6.1858,
                "Y": 6.2033,
                "FrameIndex": 420,
                "EasingData": {
                  "Type": 0
                },
                "ctype": "ScaleValueFrameData"
              },
              {
                "X": 0.0,
                "Y": 0.0,
                "FrameIndex": 435,
                "EasingData": {
                  "Type": 0
                },
                "ctype": "ScaleValueFrameData"
              },
              {
                "X": -6.6723,
                "Y": -6.6624,
                "FrameIndex": 450,
                "EasingData": {
                  "Type": 0
                },
                "ctype": "ScaleValueFrameData"
              },
              {
                "X": 0.0,
                "Y": 0.0,
                "FrameIndex": 465,
                "EasingData": {
                  "Type": 0
                },
                "ctype": "ScaleValueFrameData"
              }
            ],
            "ctype": "TimelineData"
          }
        ],
        "ctype": "TimelineActionData"
      },
      "AnimationList": [
        {
          "StartIndex": 0,
          "EndIndex": 400,
          "Name": "master",
          "ctype": "AnimationInfoData"
        },
        {
          "StartIndex": 405,
          "EndIndex": 465,
          "Name": "face",
          "ctype": "AnimationInfoData"
        },
        {
          "StartIndex": 470,
          "EndIndex": 530,
          "Name": "cloud",
          "ctype": "AnimationInfoData"
        },
        {
          "StartIndex": 535,
          "EndIndex": 575,
          "Name": "tree",
          "ctype": "AnimationInfoData"
        }
      ],
      "ObjectData": {
        "Tag": 170,
        "Children": [
          {
            "ClipAble": false,
            "ComboBoxIndex": 1,
            "SingleColor": {
              "R": 216,
              "G": 219,
              "B": 153
            },
            "FirstColor": {
              "R": 150,
              "G": 200
            },
            "EndColor": {},
            "ColorVector": {
              "ScaleY": 1.0
            },
            "Scale9Width": 1,
            "Scale9Height": 1,
            "AnchorPoint": {},
            "Position": {
              "X": -272.124,
              "Y": 596.7993
            },
            "Scale": {
              "ScaleX": 1.0,
              "ScaleY": 1.0
            },
            "CColor": {},
            "IconVisible": false,
            "PrePosition": {
              "X": -0.1063,
              "Y": 0.3316
            },
            "PreSize": {
              "X": 1.2109,
              "Y": 0.6667
            },
            "LeftMargin": -272.124,
            "RightMargin": -267.876,
            "TopMargin": 3.2007,
            "BottomMargin": 596.7993,
            "Tag": 171,
            "ActionTag": -1920652565,
            "Size": {
              "X": 3100.0,
              "Y": 1200.0
            },
            "Name": "Panel_1",
            "ctype": "PanelObjectData"
          },
          {
            "FileData": {
              "Type": "MarkedSubImage",
              "Path": "Adun_the_beautiful/adun_grass.png",
              "Plist": "Adun_the_beautiful/Adun_the_beautiful.plist"
            },
            "BlendFunc": {
              "Src": 1,
              "Dst": 771
            },
            "AnchorPoint": {
              "ScaleX": 0.5,
              "ScaleY": 0.5
            },
            "Position": {
              "X": 509.0354,
              "Y": 436.785
            },
            "Scale": {
              "ScaleX": 1.2196,
              "ScaleY": 1.9065
            },
            "CColor": {},
            "IconVisible": false,
            "PrePosition": {
              "X": 0.1988,
              "Y": 0.2427
            },
            "PreSize": {
              "X": 0.5004,
              "Y": 0.2544
            },
            "LeftMargin": -131.4646,
            "RightMargin": 1410.4646,
            "TopMargin": 1134.215,
            "BottomMargin": 207.785,
            "Tag": 183,
            "ActionTag": -2127812586,
            "Size": {
              "X": 1281.0,
              "Y": 458.0
            },
            "Name": "grass_12",
            "ctype": "SpriteObjectData"
          },
          {
            "FlipX": true,
            "FileData": {
              "Type": "MarkedSubImage",
              "Path": "Adun_the_beautiful/adun_grass.png",
              "Plist": "Adun_the_beautiful/Adun_the_beautiful.plist"
            },
            "BlendFunc": {
              "Src": 1,
              "Dst": 771
            },
            "AnchorPoint": {
              "ScaleX": 0.5,
              "ScaleY": 0.5
            },
            "Position": {
              "X": 2009.6241,
              "Y": 437.0528
            },
            "Scale": {
              "ScaleX": 1.2801,
              "ScaleY": 1.9065
            },
            "CColor": {},
            "IconVisible": false,
            "PrePosition": {
              "X": 0.785,
              "Y": 0.2428
            },
            "PreSize": {
              "X": 0.5004,
              "Y": 0.2544
            },
            "LeftMargin": 1369.1241,
            "RightMargin": -90.124,
            "TopMargin": 1133.9473,
            "BottomMargin": 208.0528,
            "Tag": 186,
            "ActionTag": -1318426924,
            "Size": {
              "X": 1281.0,
              "Y": 458.0
            },
            "Name": "grass_15",
            "ctype": "SpriteObjectData"
          },
          {
            "FileData": {
              "Type": "MarkedSubImage",
              "Path": "Adun_the_beautiful/adun_cloud.png",
              "Plist": "Adun_the_beautiful/Adun_the_beautiful.plist"
            },
            "BlendFunc": {
              "Src": 1,
              "Dst": 771
            },
            "AnchorPoint": {
              "ScaleX": 0.5,
              "ScaleY": 0.5
            },
            "Position": {
              "X": 1138.797,
              "Y": 1616.1449
            },
            "Scale": {
              "ScaleX": 1.0,
              "ScaleY": 1.0
            },
            "CColor": {},
            "IconVisible": false,
            "PrePosition": {
              "X": 0.4448,
              "Y": 0.8979
            },
            "PreSize": {
              "X": 0.2531,
              "Y": 0.1444
            },
            "LeftMargin": 814.797,
            "RightMargin": 1097.203,
            "TopMargin": 53.8551,
            "BottomMargin": 1486.1449,
            "UserData": "main.cloud",
            "Tag": 733,
            "ActionTag": -805711903,
            "Size": {
              "X": 648.0,
              "Y": 260.0
            },
            "Name": "adun_cloud_1",
            "ctype": "SpriteObjectData"
          },
          {
            "FileData": {
              "Type": "MarkedSubImage",
              "Path": "Adun_the_beautiful/adun_tree.png",
              "Plist": "Adun_the_beautiful/Adun_the_beautiful.plist"
            },
            "BlendFunc": {
              "Src": 1,
              "Dst": 771
            },
            "AnchorPoint": {
              "ScaleX": 0.5
            },
            "Position": {
              "X": 558.5298,
              "Y": 762.2684
            },
            "Scale": {
              "ScaleX": 1.5923,
              "ScaleY": 1.5923
            },
            "CColor": {},
            "IconVisible": false,
            "PrePosition": {
              "X": 0.2182,
              "Y": 0.4235
            },
            "PreSize": {
              "X": 0.1891,
              "Y": 0.2894
            },
            "LeftMargin": 316.5298,
            "RightMargin": 1759.4702,
            "TopMargin": 516.7317,
            "BottomMargin": 762.2684,
            "UserData": "main.tree",
            "Tag": 187,
            "ActionTag": -1670027600,
            "Size": {
              "X": 484.0,
              "Y": 521.0
            },
            "Name": "adun_tree_16",
            "ctype": "SpriteObjectData"
          },
          {
            "FileData": {
              "Type": "MarkedSubImage",
              "Path": "Adun_the_beautiful/adun_tree.png",
              "Plist": "Adun_the_beautiful/Adun_the_beautiful.plist"
            },
            "BlendFunc": {
              "Src": 1,
              "Dst": 771
            },
            "AnchorPoint": {
              "ScaleX": 0.5,
              "ScaleY": 0.5
            },
            "Position": {
              "X": 1950.2296,
              "Y": 1172.9133
            },
            "Scale": {
              "ScaleX": 2.0909,
              "ScaleY": 2.0909
            },
            "CColor": {},
            "IconVisible": false,
            "PrePosition": {
              "X": 0.7618,
              "Y": 0.6516
            },
            "PreSize": {
              "X": 0.1891,
              "Y": 0.2894
            },
            "LeftMargin": 1708.2296,
            "RightMargin": 367.7705,
            "TopMargin": 366.5867,
            "BottomMargin": 912.4133,
            "Tag": 188,
            "ActionTag": 404081381,
            "Size": {
              "X": 484.0,
              "Y": 521.0
            },
            "Name": "adun_tree_17",
            "ctype": "SpriteObjectData"
          },
          {
            "FileData": {
              "Type": "Normal",
              "Path": "Adun_the_beautiful/girl.json",
              "Plist": ""
            },
            "StretchWidthEnable": false,
            "StretchHeightEnable": false,
            "InnerActionSpeed": 1.0,
            "AnchorPoint": {},
            "Position": {
              "X": 236.6998,
              "Y": 422.4302
            },
            "Scale": {
              "ScaleX": -0.6345,
              "ScaleY": 0.6345
            },
            "CColor": {},
            "IconVisible": true,
            "PrePosition": {
              "X": 0.0925,
              "Y": 0.2347
            },
            "PreSize": {
              "X": 0.0,
              "Y": 0.0
            },
            "LeftMargin": 236.6998,
            "RightMargin": 2323.3003,
            "TopMargin": 1377.5698,
            "BottomMargin": 422.4302,
            "UserData": "walk;drag",
            "Tag": 932,
            "FrameEvent": "walking",
            "ActionTag": 291253660,
            "Size": {
              "X": 0.0,
              "Y": 0.0
            },
            "Name": "girl",
            "ctype": "ProjectNodeObjectData"
          },
          {
            "FileData": {
              "Type": "MarkedSubImage",
              "Path": "Adun_the_beautiful/face .png",
              "Plist": "Adun_the_beautiful/Adun_the_beautiful.plist"
            },
            "BlendFunc": {
              "Src": 1,
              "Dst": 771
            },
            "AnchorPoint": {
              "ScaleX": 0.5,
              "ScaleY": 0.5
            },
            "Position": {
              "X": 1948.5369,
              "Y": 472.4778
            },
            "Scale": {
              "ScaleX": 0.5064,
              "ScaleY": 0.5064
            },
            "CColor": {},
            "IconVisible": false,
            "PrePosition": {
              "X": 0.7611,
              "Y": 0.2625
            },
            "PreSize": {
              "X": 0.2555,
              "Y": 0.2933
            },
            "LeftMargin": 1621.5369,
            "RightMargin": 284.4631,
            "TopMargin": 1063.5222,
            "BottomMargin": 208.4778,
            "UserData": "main.face",
            "Tag": 875,
            "ActionTag": 1625798699,
            "Size": {
              "X": 654.0,
              "Y": 528.0
            },
            "Name": "Sprite_2",
            "ctype": "SpriteObjectData"
          },
          {
            "FileData": {
              "Type": "MarkedSubImage",
              "Path": "Adun_the_beautiful/motu_shirt.png",
              "Plist": "Adun_the_beautiful/Adun_the_beautiful.plist"
            },
            "BlendFunc": {
              "Src": 1,
              "Dst": 771
            },
            "AnchorPoint": {
              "ScaleX": 0.5,
              "ScaleY": 0.5
            },
            "Position": {
              "X": 1939.7965,
              "Y": 206.3887
            },
            "Scale": {
              "ScaleX": 0.481,
              "ScaleY": 0.481
            },
            "CColor": {},
            "IconVisible": false,
            "PrePosition": {
              "X": 0.7577,
              "Y": 0.1147
            },
            "PreSize": {
              "X": 0.1676,
              "Y": 0.3256
            },
            "LeftMargin": 1725.2965,
            "RightMargin": 405.7036,
            "TopMargin": 1300.6113,
            "BottomMargin": -86.6113,
            "Tag": 1451,
            "ActionTag": 679795344,
            "Size": {
              "X": 429.0,
              "Y": 586.0
            },
            "Name": "motu_shirt_104",
            "ctype": "SpriteObjectData"
          },
          {
            "FileData": {
              "Type": "MarkedSubImage",
              "Path": "Adun_the_beautiful/girl_upper_hand.png",
              "Plist": "Adun_the_beautiful/Adun_the_beautiful.plist"
            },
            "BlendFunc": {
              "Src": 1,
              "Dst": 771
            },
            "AnchorPoint": {
              "ScaleX": 0.5,
              "ScaleY": 0.5
            },
            "Position": {
              "X": 1797.6102,
              "Y": 265.8678
            },
            "Scale": {
              "ScaleX": 1.0,
              "ScaleY": 1.0
            },
            "RotationSkewX": 59.5784,
            "RotationSkewY": 59.5793,
            "CColor": {},
            "IconVisible": false,
            "PrePosition": {
              "X": 0.7022,
              "Y": 0.1477
            },
            "PreSize": {
              "X": 0.0109,
              "Y": 0.0983
            },
            "LeftMargin": 1783.6102,
            "RightMargin": 748.3898,
            "TopMargin": 1445.6322,
            "BottomMargin": 177.3678,
            "Tag": 1452,
            "ActionTag": 161268316,
            "Size": {
              "X": 28.0,
              "Y": 177.0
            },
            "Name": "girl_upper_hand_105",
            "ctype": "SpriteObjectData"
          },
          {
            "FileData": {
              "Type": "MarkedSubImage",
              "Path": "Adun_the_beautiful/girl_upper_hand.png",
              "Plist": "Adun_the_beautiful/Adun_the_beautiful.plist"
            },
            "BlendFunc": {
              "Src": 1,
              "Dst": 771
            },
            "AnchorPoint": {
              "ScaleX": 0.5,
              "ScaleY": 0.5
            },
            "Position": {
              "X": 1952.8501,
              "Y": 244.7672
            },
            "Scale": {
              "ScaleX": 1.0,
              "ScaleY": 1.0
            },
            "RotationSkewX": 63.4467,
            "RotationSkewY": 63.4396,
            "CColor": {},
            "IconVisible": false,
            "PrePosition": {
              "X": 0.7628,
              "Y": 0.136
            },
            "PreSize": {
              "X": 0.0109,
              "Y": 0.0983
            },
            "LeftMargin": 1938.8501,
            "RightMargin": 593.1499,
            "TopMargin": 1466.7328,
            "BottomMargin": 156.2672,
            "Tag": 1453,
            "ActionTag": 1654780540,
            "Size": {
              "X": 28.0,
              "Y": 177.0
            },
            "Name": "girl_upper_hand_106",
            "ctype": "SpriteObjectData"
          },
          {
            "FileData": {
              "Type": "MarkedSubImage",
              "Path": "Adun_the_beautiful/motu_pant_lower_left.png",
              "Plist": "Adun_the_beautiful/Adun_the_beautiful.plist"
            },
            "BlendFunc": {
              "Src": 1,
              "Dst": 771
            },
            "AnchorPoint": {
              "ScaleX": 0.5,
              "ScaleY": 0.5
            },
            "Position": {
              "X": 1804.4014,
              "Y": 268.3274
            },
            "Scale": {
              "ScaleX": 1.0,
              "ScaleY": 1.0
            },
            "RotationSkewX": 103.5731,
            "RotationSkewY": 103.5765,
            "CColor": {},
            "IconVisible": false,
            "PrePosition": {
              "X": 0.7048,
              "Y": 0.1491
            },
            "PreSize": {
              "X": 0.0117,
              "Y": 0.0533
            },
            "LeftMargin": 1789.4014,
            "RightMargin": 740.5986,
            "TopMargin": 1483.6726,
            "BottomMargin": 220.3274,
            "Tag": 1454,
            "ActionTag": 1628908774,
            "Size": {
              "X": 30.0,
              "Y": 96.0
            },
            "Name": "motu_pant_lower_left_107",
            "ctype": "SpriteObjectData"
          },
          {
            "FileData": {
              "Type": "MarkedSubImage",
              "Path": "Adun_the_beautiful/motu_pant_upper_left.png",
              "Plist": "Adun_the_beautiful/Adun_the_beautiful.plist"
            },
            "BlendFunc": {
              "Src": 1,
              "Dst": 771
            },
            "AnchorPoint": {
              "ScaleX": 0.5,
              "ScaleY": 0.5
            },
            "Position": {
              "X": 1895.1558,
              "Y": 245.3281
            },
            "Scale": {
              "ScaleX": 1.0,
              "ScaleY": 1.0
            },
            "RotationSkewX": 103.5723,
            "RotationSkewY": 103.5763,
            "CColor": {},
            "IconVisible": false,
            "PrePosition": {
              "X": 0.7403,
              "Y": 0.1363
            },
            "PreSize": {
              "X": 0.0141,
              "Y": 0.0817
            },
            "LeftMargin": 1877.1558,
            "RightMargin": 646.8442,
            "TopMargin": 1481.1719,
            "BottomMargin": 171.8281,
            "Tag": 1455,
            "ActionTag": 68228908,
            "Size": {
              "X": 36.0,
              "Y": 147.0
            },
            "Name": "motu_pant_upper_left_108",
            "ctype": "SpriteObjectData"
          },
          {
            "FileData": {
              "Type": "MarkedSubImage",
              "Path": "Adun_the_beautiful/motu_shoes_left.png",
              "Plist": "Adun_the_beautiful/Adun_the_beautiful.plist"
            },
            "BlendFunc": {
              "Src": 1,
              "Dst": 771
            },
            "AnchorPoint": {
              "ScaleX": 0.5,
              "ScaleY": 0.5
            },
            "Position": {
              "X": 1766.2499,
              "Y": 339.3383
            },
            "Scale": {
              "ScaleX": 1.0,
              "ScaleY": 1.0
            },
            "RotationSkewX": 101.6573,
            "RotationSkewY": 101.6696,
            "CColor": {},
            "IconVisible": false,
            "PrePosition": {
              "X": 0.6899,
              "Y": 0.1885
            },
            "PreSize": {
              "X": 0.0621,
              "Y": 0.0183
            },
            "LeftMargin": 1686.7499,
            "RightMargin": 714.2501,
            "TopMargin": 1444.1617,
            "BottomMargin": 322.8383,
            "Tag": 1456,
            "ActionTag": -2126625813,
            "Size": {
              "X": 159.0,
              "Y": 33.0
            },
            "Name": "motu_shoes_left_109",
            "ctype": "SpriteObjectData"
          },
          {
            "FileData": {
              "Type": "MarkedSubImage",
              "Path": "Adun_the_beautiful/motu_pant_lower_left.png",
              "Plist": "Adun_the_beautiful/Adun_the_beautiful.plist"
            },
            "BlendFunc": {
              "Src": 1,
              "Dst": 771
            },
            "AnchorPoint": {
              "ScaleX": 0.5,
              "ScaleY": 0.5
            },
            "Position": {
              "X": 1752.8391,
              "Y": 231.6112
            },
            "Scale": {
              "ScaleX": 1.0,
              "ScaleY": 1.0
            },
            "RotationSkewX": 103.5731,
            "RotationSkewY": 103.5763,
            "CColor": {},
            "IconVisible": false,
            "PrePosition": {
              "X": 0.6847,
              "Y": 0.1287
            },
            "PreSize": {
              "X": 0.0117,
              "Y": 0.0533
            },
            "LeftMargin": 1737.8391,
            "RightMargin": 792.1609,
            "TopMargin": 1520.3888,
            "BottomMargin": 183.6112,
            "Tag": 1457,
            "ActionTag": -551272514,
            "Size": {
              "X": 30.0,
              "Y": 96.0
            },
            "Name": "motu_pant_lower_left_107_0",
            "ctype": "SpriteObjectData"
          },
          {
            "FileData": {
              "Type": "MarkedSubImage",
              "Path": "Adun_the_beautiful/motu_pant_upper_left.png",
              "Plist": "Adun_the_beautiful/Adun_the_beautiful.plist"
            },
            "BlendFunc": {
              "Src": 1,
              "Dst": 771
            },
            "AnchorPoint": {
              "ScaleX": 0.5,
              "ScaleY": 0.5
            },
            "Position": {
              "X": 1843.593,
              "Y": 208.6095
            },
            "Scale": {
              "ScaleX": 1.0,
              "ScaleY": 1.0
            },
            "RotationSkewX": 103.5757,
            "RotationSkewY": 103.5763,
            "CColor": {},
            "IconVisible": false,
            "PrePosition": {
              "X": 0.7202,
              "Y": 0.1159
            },
            "PreSize": {
              "X": 0.0141,
              "Y": 0.0817
            },
            "LeftMargin": 1825.593,
            "RightMargin": 698.407,
            "TopMargin": 1517.8905,
            "BottomMargin": 135.1095,
            "Tag": 1458,
            "ActionTag": -566226802,
            "Size": {
              "X": 36.0,
              "Y": 147.0
            },
            "Name": "motu_pant_upper_left_108_0",
            "ctype": "SpriteObjectData"
          },
          {
            "FileData": {
              "Type": "MarkedSubImage",
              "Path": "Adun_the_beautiful/motu_shoes_left.png",
              "Plist": "Adun_the_beautiful/Adun_the_beautiful.plist"
            },
            "BlendFunc": {
              "Src": 1,
              "Dst": 771
            },
            "AnchorPoint": {
              "ScaleX": 0.5,
              "ScaleY": 0.5
            },
            "Position": {
              "X": 1714.6927,
              "Y": 302.6207
            },
            "Scale": {
              "ScaleX": 1.0,
              "ScaleY": 1.0
            },
            "RotationSkewX": 101.6573,
            "RotationSkewY": 101.6696,
            "CColor": {},
            "IconVisible": false,
            "PrePosition": {
              "X": 0.6698,
              "Y": 0.1681
            },
            "PreSize": {
              "X": 0.0621,
              "Y": 0.0183
            },
            "LeftMargin": 1635.1927,
            "RightMargin": 765.8073,
            "TopMargin": 1480.8793,
            "BottomMargin": 286.1207,
            "Tag": 1459,
            "ActionTag": 1412524157,
            "Size": {
              "X": 159.0,
              "Y": 33.0
            },
            "Name": "motu_shoes_left_109_0",
            "ctype": "SpriteObjectData"
          },
          {
            "FlipX": true,
            "FileData": {
              "Type": "MarkedSubImage",
              "Path": "Adun_the_beautiful/face .png",
              "Plist": "Adun_the_beautiful/Adun_the_beautiful.plist"
            },
            "BlendFunc": {
              "Src": 1,
              "Dst": 771
            },
            "AnchorPoint": {
              "ScaleX": 0.5,
              "ScaleY": 0.5
            },
            "Position": {
              "X": 1336.1726,
              "Y": 453.986
            },
            "Scale": {
              "ScaleX": 0.5064,
              "ScaleY": 0.5064
            },
            "CColor": {},
            "IconVisible": false,
            "PrePosition": {
              "X": 0.5219,
              "Y": 0.2522
            },
            "PreSize": {
              "X": 0.2555,
              "Y": 0.2933
            },
            "LeftMargin": 1009.1726,
            "RightMargin": 896.8274,
            "TopMargin": 1082.014,
            "BottomMargin": 189.986,
            "UserData": "main.face",
            "Tag": 1460,
            "ActionTag": -1797262533,
            "Size": {
              "X": 654.0,
              "Y": 528.0
            },
            "Name": "Sprite_113",
            "ctype": "SpriteObjectData"
          },
          {
            "FileData": {
              "Type": "MarkedSubImage",
              "Path": "Adun_the_beautiful/shirt1.png",
              "Plist": "Adun_the_beautiful/Adun_the_beautiful.plist"
            },
            "BlendFunc": {
              "Src": 1,
              "Dst": 771
            },
            "AnchorPoint": {
              "ScaleX": 0.5,
              "ScaleY": 0.5
            },
            "Position": {
              "X": 1347.7988,
              "Y": 189.495
            },
            "Scale": {
              "ScaleX": 0.6456,
              "ScaleY": 0.6456
            },
            "CColor": {},
            "IconVisible": false,
            "PrePosition": {
              "X": 0.5265,
              "Y": 0.1053
            },
            "PreSize": {
              "X": 0.1211,
              "Y": 0.2383
            },
            "LeftMargin": 1192.7988,
            "RightMargin": 1057.2012,
            "TopMargin": 1396.005,
            "BottomMargin": -25.005,
            "Tag": 1461,
            "ActionTag": -933428992,
            "Size": {
              "X": 310.0,
              "Y": 429.0
            },
            "Name": "shirt1_114",
            "ctype": "SpriteObjectData"
          },
          {
            "FileData": {
              "Type": "MarkedSubImage",
              "Path": "Adun_the_beautiful/girl_upper_hand.png",
              "Plist": "Adun_the_beautiful/Adun_the_beautiful.plist"
            },
            "BlendFunc": {
              "Src": 1,
              "Dst": 771
            },
            "AnchorPoint": {
              "ScaleX": 0.5,
              "ScaleY": 0.5
            },
            "Position": {
              "X": 1332.3953,
              "Y": 200.1146
            },
            "Scale": {
              "ScaleX": 1.0,
              "ScaleY": 1.0
            },
            "RotationSkewX": -47.5132,
            "RotationSkewY": -47.5138,
            "CColor": {},
            "IconVisible": false,
            "PrePosition": {
              "X": 0.5205,
              "Y": 0.1112
            },
            "PreSize": {
              "X": 0.0109,
              "Y": 0.0983
            },
            "LeftMargin": 1318.3953,
            "RightMargin": 1213.6047,
            "TopMargin": 1511.3854,
            "BottomMargin": 111.6146,
            "Tag": 1462,
            "ActionTag": -1241779470,
            "Size": {
              "X": 28.0,
              "Y": 177.0
            },
            "Name": "girl_upper_hand_115",
            "ctype": "SpriteObjectData"
          },
          {
            "FileData": {
              "Type": "MarkedSubImage",
              "Path": "Adun_the_beautiful/girl_upper_hand.png",
              "Plist": "Adun_the_beautiful/Adun_the_beautiful.plist"
            },
            "BlendFunc": {
              "Src": 1,
              "Dst": 771
            },
            "AnchorPoint": {
              "ScaleX": 0.5,
              "ScaleY": 0.5
            },
            "Position": {
              "X": 1491.4514,
              "Y": 224.0703
            },
            "Scale": {
              "ScaleX": 1.0,
              "ScaleY": 1.0
            },
            "RotationSkewX": -65.3574,
            "RotationSkewY": -65.3398,
            "CColor": {},
            "IconVisible": false,
            "PrePosition": {
              "X": 0.5826,
              "Y": 0.1245
            },
            "PreSize": {
              "X": 0.0109,
              "Y": 0.0983
            },
            "LeftMargin": 1477.4514,
            "RightMargin": 1054.5486,
            "TopMargin": 1487.4297,
            "BottomMargin": 135.5703,
            "Tag": 1463,
            "ActionTag": 1516766293,
            "Size": {
              "X": 28.0,
              "Y": 177.0
            },
            "Name": "girl_upper_hand_116",
            "ctype": "SpriteObjectData"
          }
        ],
        "Size": {
          "X": 2560.0,
          "Y": 1800.0
        },
        "Name": "Scene",
        "ctype": "SingleNodeObjectData"
      },
      "UsedResources": [
        "Adun_the_beautiful.plist",
        "Adun_the_beautiful.png",
        "girl.json"
      ],
      "ctype": "GameFileData"
    }
  },
  "Type": "Scene"
}