{
  "ID": "466ff002-e12e-4873-82fd-cffe098d6a6b",
  "Version": "3.10.0.0",
  "Name": "Mpirawangumwekundu16",
  "Content": {
    "Content": {
      "Animation": {
        "Duration": 320,
        "Speed": 1.0,
        "ActivedAnimationName": "master",
        "Timelines": [
          {
            "ActionTag": 478460844,
            "Property": "Position",
            "Frames": [
              {
                "X": 1301.9417,
                "Y": 875.5494,
                "FrameIndex": 0,
                "EasingData": {
                  "Type": 0
                },
                "ctype": "PointFrameData"
              },
              {
                "X": 1301.9399,
                "Y": 875.55,
                "FrameIndex": 45,
                "EasingData": {
                  "Type": 0
                },
                "ctype": "PointFrameData"
              },
              {
                "X": 1301.9399,
                "Y": 875.55,
                "FrameIndex": 175,
                "EasingData": {
                  "Type": 0
                },
                "ctype": "PointFrameData"
              }
            ],
            "ctype": "TimelineData"
          },
          {
            "ActionTag": 478460844,
            "Property": "Scale",
            "Frames": [
              {
                "X": 1.5595,
                "Y": 1.5595,
                "FrameIndex": 175,
                "EasingData": {
                  "Type": 0
                },
                "ctype": "ScaleValueFrameData"
              }
            ],
            "ctype": "TimelineData"
          },
          {
            "ActionTag": 478460844,
            "Property": "RotationSkew",
            "Frames": [
              {
                "X": 1.6686,
                "Y": 1.6686,
                "FrameIndex": 0,
                "EasingData": {
                  "Type": 0
                },
                "ctype": "ScaleValueFrameData"
              },
              {
                "X": 1.6686,
                "Y": 1.6686,
                "FrameIndex": 45,
                "EasingData": {
                  "Type": 0
                },
                "ctype": "ScaleValueFrameData"
              },
              {
                "X": 1.6507,
                "Y": 1.6507,
                "FrameIndex": 175,
                "EasingData": {
                  "Type": 0
                },
                "ctype": "ScaleValueFrameData"
              }
            ],
            "ctype": "TimelineData"
          },
          {
            "ActionTag": 478460844,
            "Property": "CColor",
            "Frames": [
              {
                "Alpha": 255,
                "Color": {
                  "R": 157,
                  "G": 146,
                  "B": 198
                },
                "FrameIndex": 0,
                "EasingData": {
                  "Type": 0
                },
                "ctype": "ColorFrameData"
              },
              {
                "Alpha": 255,
                "Color": {
                  "R": 157,
                  "G": 146,
                  "B": 198
                },
                "FrameIndex": 180,
                "EasingData": {
                  "Type": 0
                },
                "ctype": "ColorFrameData"
              },
              {
                "Alpha": 255,
                "Color": {},
                "FrameIndex": 320,
                "EasingData": {
                  "Type": 0
                },
                "ctype": "ColorFrameData"
              }
            ],
            "ctype": "TimelineData"
          },
          {
            "ActionTag": 757041886,
            "Property": "Position",
            "Frames": [
              {
                "X": 2083.1702,
                "Y": 1579.0547,
                "FrameIndex": 0,
                "EasingData": {
                  "Type": 0
                },
                "ctype": "PointFrameData"
              },
              {
                "X": 2083.1702,
                "Y": 1579.0547,
                "FrameIndex": 45,
                "EasingData": {
                  "Type": 0
                },
                "ctype": "PointFrameData"
              },
              {
                "X": 2015.9944,
                "Y": 1594.923,
                "FrameIndex": 175,
                "EasingData": {
                  "Type": 0
                },
                "ctype": "PointFrameData"
              },
              {
                "X": 2015.9966,
                "Y": 1595.9241,
                "FrameIndex": 180,
                "EasingData": {
                  "Type": 0
                },
                "ctype": "PointFrameData"
              },
              {
                "X": 1258.1357,
                "Y": 800.1611,
                "FrameIndex": 320,
                "EasingData": {
                  "Type": 0
                },
                "ctype": "PointFrameData"
              }
            ],
            "ctype": "TimelineData"
          },
          {
            "ActionTag": 757041886,
            "Property": "Scale",
            "Frames": [
              {
                "X": 0.8541,
                "Y": 0.8541,
                "FrameIndex": 175,
                "EasingData": {
                  "Type": 0
                },
                "ctype": "ScaleValueFrameData"
              }
            ],
            "ctype": "TimelineData"
          },
          {
            "ActionTag": 757041886,
            "Property": "RotationSkew",
            "Frames": [
              {
                "X": 1.7077,
                "Y": 1.6632,
                "FrameIndex": 0,
                "EasingData": {
                  "Type": 0
                },
                "ctype": "ScaleValueFrameData"
              },
              {
                "X": 1.7077,
                "Y": 1.6632,
                "FrameIndex": 45,
                "EasingData": {
                  "Type": 0
                },
                "ctype": "ScaleValueFrameData"
              },
              {
                "X": 1.6052,
                "Y": 1.7198,
                "FrameIndex": 175,
                "EasingData": {
                  "Type": 0
                },
                "ctype": "ScaleValueFrameData"
              },
              {
                "X": 5.1744,
                "Y": 5.2893,
                "FrameIndex": 180,
                "EasingData": {
                  "Type": 0
                },
                "ctype": "ScaleValueFrameData"
              },
              {
                "X": -9.776,
                "Y": -9.6683,
                "FrameIndex": 320,
                "EasingData": {
                  "Type": 0
                },
                "ctype": "ScaleValueFrameData"
              }
            ],
            "ctype": "TimelineData"
          },
          {
            "ActionTag": 656915679,
            "Property": "Position",
            "Frames": [
              {
                "X": 1207.1929,
                "Y": -308.4509,
                "FrameIndex": 0,
                "EasingData": {
                  "Type": 0
                },
                "ctype": "PointFrameData"
              },
              {
                "X": 1207.1929,
                "Y": -308.4509,
                "FrameIndex": 45,
                "EasingData": {
                  "Type": 0
                },
                "ctype": "PointFrameData"
              },
              {
                "X": 1294.7231,
                "Y": -119.8163,
                "FrameIndex": 175,
                "EasingData": {
                  "Type": 0
                },
                "ctype": "PointFrameData"
              }
            ],
            "ctype": "TimelineData"
          },
          {
            "ActionTag": 656915679,
            "Property": "Scale",
            "Frames": [
              {
                "X": 1.4637,
                "Y": 1.2606,
                "FrameIndex": 175,
                "EasingData": {
                  "Type": 0
                },
                "ctype": "ScaleValueFrameData"
              }
            ],
            "ctype": "TimelineData"
          },
          {
            "ActionTag": 656915679,
            "Property": "RotationSkew",
            "Frames": [
              {
                "X": -3.3458,
                "Y": -2.0399,
                "FrameIndex": 0,
                "EasingData": {
                  "Type": 0
                },
                "ctype": "ScaleValueFrameData"
              },
              {
                "X": -3.3458,
                "Y": -2.0399,
                "FrameIndex": 45,
                "EasingData": {
                  "Type": 0
                },
                "ctype": "ScaleValueFrameData"
              },
              {
                "X": -3.3586,
                "Y": -2.0301,
                "FrameIndex": 175,
                "EasingData": {
                  "Type": 0
                },
                "ctype": "ScaleValueFrameData"
              }
            ],
            "ctype": "TimelineData"
          },
          {
            "ActionTag": -360271639,
            "Property": "Position",
            "Frames": [
              {
                "X": 1200.1714,
                "Y": 265.7455,
                "FrameIndex": 0,
                "EasingData": {
                  "Type": 0
                },
                "ctype": "PointFrameData"
              },
              {
                "X": 1200.1714,
                "Y": 265.7455,
                "FrameIndex": 45,
                "EasingData": {
                  "Type": 0
                },
                "ctype": "PointFrameData"
              },
              {
                "X": 1287.1084,
                "Y": 503.7246,
                "FrameIndex": 175,
                "EasingData": {
                  "Type": 0
                },
                "ctype": "PointFrameData"
              }
            ],
            "ctype": "TimelineData"
          },
          {
            "ActionTag": -360271639,
            "Property": "Scale",
            "Frames": [
              {
                "X": 1.4647,
                "Y": 0.1729,
                "FrameIndex": 175,
                "EasingData": {
                  "Type": 0
                },
                "ctype": "ScaleValueFrameData"
              }
            ],
            "ctype": "TimelineData"
          },
          {
            "ActionTag": -360271639,
            "Property": "RotationSkew",
            "Frames": [
              {
                "X": 1.4936,
                "Y": 1.4663,
                "FrameIndex": 0,
                "EasingData": {
                  "Type": 0
                },
                "ctype": "ScaleValueFrameData"
              },
              {
                "X": 1.4936,
                "Y": 1.4663,
                "FrameIndex": 45,
                "EasingData": {
                  "Type": 0
                },
                "ctype": "ScaleValueFrameData"
              },
              {
                "X": 1.3755,
                "Y": 1.4697,
                "FrameIndex": 175,
                "EasingData": {
                  "Type": 0
                },
                "ctype": "ScaleValueFrameData"
              }
            ],
            "ctype": "TimelineData"
          },
          {
            "ActionTag": -347262882,
            "Property": "Position",
            "Frames": [
              {
                "X": 2176.0208,
                "Y": 243.634,
                "FrameIndex": 0,
                "EasingData": {
                  "Type": 0
                },
                "ctype": "PointFrameData"
              },
              {
                "X": 2176.0208,
                "Y": 243.634,
                "FrameIndex": 45,
                "EasingData": {
                  "Type": 0
                },
                "ctype": "PointFrameData"
              },
              {
                "X": 2346.8237,
                "Y": 479.7136,
                "FrameIndex": 175,
                "EasingData": {
                  "Type": 0
                },
                "ctype": "PointFrameData"
              }
            ],
            "ctype": "TimelineData"
          },
          {
            "ActionTag": -347262882,
            "Property": "Scale",
            "Frames": [
              {
                "X": 0.4948,
                "Y": 0.4948,
                "FrameIndex": 175,
                "EasingData": {
                  "Type": 0
                },
                "ctype": "ScaleValueFrameData"
              }
            ],
            "ctype": "TimelineData"
          },
          {
            "ActionTag": -347262882,
            "Property": "RotationSkew",
            "Frames": [
              {
                "X": 1.6889,
                "Y": 1.6719,
                "FrameIndex": 0,
                "EasingData": {
                  "Type": 0
                },
                "ctype": "ScaleValueFrameData"
              },
              {
                "X": 1.6889,
                "Y": 1.6719,
                "FrameIndex": 45,
                "EasingData": {
                  "Type": 0
                },
                "ctype": "ScaleValueFrameData"
              },
              {
                "X": 1.5552,
                "Y": 1.6716,
                "FrameIndex": 175,
                "EasingData": {
                  "Type": 0
                },
                "ctype": "ScaleValueFrameData"
              }
            ],
            "ctype": "TimelineData"
          },
          {
            "ActionTag": 1712206912,
            "Property": "Position",
            "Frames": [
              {
                "X": 103.8972,
                "Y": 750.779,
                "FrameIndex": 0,
                "EasingData": {
                  "Type": 0
                },
                "ctype": "PointFrameData"
              },
              {
                "X": 103.8972,
                "Y": 750.779,
                "FrameIndex": 45,
                "EasingData": {
                  "Type": 0
                },
                "ctype": "PointFrameData"
              },
              {
                "X": 96.6123,
                "Y": 1030.448,
                "FrameIndex": 175,
                "EasingData": {
                  "Type": 0
                },
                "ctype": "PointFrameData"
              }
            ],
            "ctype": "TimelineData"
          },
          {
            "ActionTag": 1712206912,
            "Property": "Scale",
            "Frames": [
              {
                "X": 0.3427,
                "Y": 0.3427,
                "FrameIndex": 175,
                "EasingData": {
                  "Type": 0
                },
                "ctype": "ScaleValueFrameData"
              }
            ],
            "ctype": "TimelineData"
          },
          {
            "ActionTag": 1712206912,
            "Property": "RotationSkew",
            "Frames": [
              {
                "X": 1.6722,
                "Y": 1.6848,
                "FrameIndex": 0,
                "EasingData": {
                  "Type": 0
                },
                "ctype": "ScaleValueFrameData"
              },
              {
                "X": 1.6722,
                "Y": 1.6848,
                "FrameIndex": 45,
                "EasingData": {
                  "Type": 0
                },
                "ctype": "ScaleValueFrameData"
              },
              {
                "X": 1.6675,
                "Y": 1.7965,
                "FrameIndex": 175,
                "EasingData": {
                  "Type": 0
                },
                "ctype": "ScaleValueFrameData"
              }
            ],
            "ctype": "TimelineData"
          },
          {
            "ActionTag": -28917437,
            "Property": "Position",
            "Frames": [
              {
                "X": 1666.6216,
                "Y": 791.8782,
                "FrameIndex": 0,
                "EasingData": {
                  "Type": 0
                },
                "ctype": "PointFrameData"
              },
              {
                "X": 1666.6216,
                "Y": 791.8782,
                "FrameIndex": 45,
                "EasingData": {
                  "Type": 0
                },
                "ctype": "PointFrameData"
              },
              {
                "X": 1793.6514,
                "Y": 1075.0784,
                "FrameIndex": 175,
                "EasingData": {
                  "Type": 0
                },
                "ctype": "PointFrameData"
              }
            ],
            "ctype": "TimelineData"
          },
          {
            "ActionTag": -28917437,
            "Property": "Scale",
            "Frames": [
              {
                "X": 0.2553,
                "Y": 0.2553,
                "FrameIndex": 175,
                "EasingData": {
                  "Type": 0
                },
                "ctype": "ScaleValueFrameData"
              }
            ],
            "ctype": "TimelineData"
          },
          {
            "ActionTag": -28917437,
            "Property": "RotationSkew",
            "Frames": [
              {
                "X": 1.6068,
                "Y": 1.6961,
                "FrameIndex": 0,
                "EasingData": {
                  "Type": 0
                },
                "ctype": "ScaleValueFrameData"
              },
              {
                "X": 1.6068,
                "Y": 1.6961,
                "FrameIndex": 45,
                "EasingData": {
                  "Type": 0
                },
                "ctype": "ScaleValueFrameData"
              },
              {
                "X": 1.4793,
                "Y": 1.5889,
                "FrameIndex": 175,
                "EasingData": {
                  "Type": 0
                },
                "ctype": "ScaleValueFrameData"
              }
            ],
            "ctype": "TimelineData"
          },
          {
            "ActionTag": 866161992,
            "Property": "ActionValue",
            "Frames": [
              {
                "InnerActionType": "LoopAction",
                "CurrentAniamtionName": "fly",
                "SingleFrameIndex": 0,
                "FrameIndex": 45,
                "Tween": false,
                "ctype": "InnerActionFrameData"
              }
            ],
            "ctype": "TimelineData"
          },
          {
            "ActionTag": 866161992,
            "Property": "Position",
            "Frames": [
              {
                "X": 1663.7603,
                "Y": 928.1396,
                "FrameIndex": 0,
                "EasingData": {
                  "Type": 0
                },
                "ctype": "PointFrameData"
              },
              {
                "X": 1663.7603,
                "Y": 928.1396,
                "FrameIndex": 45,
                "EasingData": {
                  "Type": 0
                },
                "ctype": "PointFrameData"
              },
              {
                "X": 1055.3258,
                "Y": 1393.8943,
                "FrameIndex": 175,
                "EasingData": {
                  "Type": 0
                },
                "ctype": "PointFrameData"
              },
              {
                "X": 1055.3258,
                "Y": 1393.8943,
                "FrameIndex": 180,
                "EasingData": {
                  "Type": 0
                },
                "ctype": "PointFrameData"
              },
              {
                "X": 277.8778,
                "Y": 1198.9634,
                "FrameIndex": 295,
                "EasingData": {
                  "Type": 0
                },
                "ctype": "PointFrameData"
              }
            ],
            "ctype": "TimelineData"
          },
          {
            "ActionTag": 866161992,
            "Property": "Scale",
            "Frames": [
              {
                "X": 0.0824,
                "Y": 0.0824,
                "FrameIndex": 0,
                "EasingData": {
                  "Type": 0
                },
                "ctype": "ScaleValueFrameData"
              },
              {
                "X": 0.0824,
                "Y": 0.0824,
                "FrameIndex": 45,
                "EasingData": {
                  "Type": 0
                },
                "ctype": "ScaleValueFrameData"
              }
            ],
            "ctype": "TimelineData"
          },
          {
            "ActionTag": -1227334959,
            "Property": "ActionValue",
            "Frames": [
              {
                "InnerActionType": "LoopAction",
                "CurrentAniamtionName": "fly",
                "SingleFrameIndex": 0,
                "FrameIndex": 45,
                "Tween": false,
                "ctype": "InnerActionFrameData"
              }
            ],
            "ctype": "TimelineData"
          },
          {
            "ActionTag": -1227334959,
            "Property": "Position",
            "Frames": [
              {
                "X": 93.3736,
                "Y": 1023.621,
                "FrameIndex": 0,
                "EasingData": {
                  "Type": 0
                },
                "ctype": "PointFrameData"
              },
              {
                "X": 93.3736,
                "Y": 1023.621,
                "FrameIndex": 45,
                "EasingData": {
                  "Type": 0
                },
                "ctype": "PointFrameData"
              },
              {
                "X": 659.7671,
                "Y": 1846.1445,
                "FrameIndex": 175,
                "EasingData": {
                  "Type": 0
                },
                "ctype": "PointFrameData"
              },
              {
                "X": 659.7671,
                "Y": 1846.1445,
                "FrameIndex": 180,
                "EasingData": {
                  "Type": 0
                },
                "ctype": "PointFrameData"
              },
              {
                "X": 917.1792,
                "Y": 1004.2678,
                "FrameIndex": 300,
                "EasingData": {
                  "Type": 0
                },
                "ctype": "PointFrameData"
              }
            ],
            "ctype": "TimelineData"
          },
          {
            "ActionTag": -1227334959,
            "Property": "Scale",
            "Frames": [
              {
                "X": -0.1162,
                "Y": 0.1162,
                "FrameIndex": 0,
                "EasingData": {
                  "Type": 0
                },
                "ctype": "ScaleValueFrameData"
              },
              {
                "X": -0.1162,
                "Y": 0.1162,
                "FrameIndex": 45,
                "EasingData": {
                  "Type": 0
                },
                "ctype": "ScaleValueFrameData"
              }
            ],
            "ctype": "TimelineData"
          },
          {
            "ActionTag": -1227334959,
            "Property": "RotationSkew",
            "Frames": [
              {
                "X": 0.0,
                "Y": 0.0043,
                "FrameIndex": 180,
                "EasingData": {
                  "Type": 0
                },
                "ctype": "ScaleValueFrameData"
              },
              {
                "X": -8.1514,
                "Y": -8.1514,
                "FrameIndex": 300,
                "EasingData": {
                  "Type": 0
                },
                "ctype": "ScaleValueFrameData"
              }
            ],
            "ctype": "TimelineData"
          },
          {
            "ActionTag": 324095046,
            "Property": "ActionValue",
            "Frames": [
              {
                "InnerActionType": "LoopAction",
                "CurrentAniamtionName": "walk",
                "SingleFrameIndex": 0,
                "FrameIndex": 0,
                "Tween": false,
                "ctype": "InnerActionFrameData"
              },
              {
                "InnerActionType": "SingleFrame",
                "CurrentAniamtionName": "walk",
                "SingleFrameIndex": 0,
                "FrameIndex": 45,
                "Tween": false,
                "ctype": "InnerActionFrameData"
              },
              {
                "InnerActionType": "SingleFrame",
                "CurrentAniamtionName": "walk",
                "SingleFrameIndex": 0,
                "FrameIndex": 175,
                "Tween": false,
                "ctype": "InnerActionFrameData"
              }
            ],
            "ctype": "TimelineData"
          },
          {
            "ActionTag": 324095046,
            "Property": "Position",
            "Frames": [
              {
                "X": 131.4918,
                "Y": -501.822,
                "FrameIndex": 0,
                "EasingData": {
                  "Type": 0
                },
                "ctype": "PointFrameData"
              },
              {
                "X": 483.5361,
                "Y": -505.0957,
                "FrameIndex": 45,
                "EasingData": {
                  "Type": 0
                },
                "ctype": "PointFrameData"
              },
              {
                "X": 719.2764,
                "Y": -418.9875,
                "FrameIndex": 175,
                "EasingData": {
                  "Type": 0
                },
                "ctype": "PointFrameData"
              }
            ],
            "ctype": "TimelineData"
          },
          {
            "ActionTag": 324095046,
            "Property": "Scale",
            "Frames": [
              {
                "X": -1.0859,
                "Y": 1.0859,
                "FrameIndex": 175,
                "EasingData": {
                  "Type": 0
                },
                "ctype": "ScaleValueFrameData"
              }
            ],
            "ctype": "TimelineData"
          }
        ],
        "ctype": "TimelineActionData"
      },
      "AnimationList": [
        {
          "StartIndex": 0,
          "EndIndex": 175,
          "Name": "master",
          "ctype": "AnimationInfoData"
        },
        {
          "StartIndex": 180,
          "EndIndex": 320,
          "Name": "night",
          "ctype": "AnimationInfoData"
        }
      ],
      "ObjectData": {
        "Tag": 1996,
        "Children": [
          {
            "ClipAble": false,
            "ComboBoxIndex": 2,
            "SingleColor": {
              "R": 173,
              "G": 147,
              "B": 228
            },
            "FirstColor": {
              "R": 133,
              "G": 164,
              "B": 254
            },
            "EndColor": {
              "R": 172,
              "G": 167
            },
            "ColorVector": {
              "ScaleY": -1.0
            },
            "Scale9Width": 1,
            "Scale9Height": 1,
            "AnchorPoint": {
              "ScaleX": 0.5,
              "ScaleY": 0.5
            },
            "Position": {
              "X": 1301.9417,
              "Y": 875.5494
            },
            "Scale": {
              "ScaleX": 1.5595,
              "ScaleY": 1.5595
            },
            "RotationSkewX": 1.6686,
            "RotationSkewY": 1.6686,
            "CColor": {
              "R": 157,
              "G": 146,
              "B": 198
            },
            "IconVisible": false,
            "PrePosition": {
              "X": 0.5086,
              "Y": 0.4864
            },
            "PreSize": {
              "X": 1.5625,
              "Y": 1.0
            },
            "LeftMargin": -698.0583,
            "RightMargin": -741.9417,
            "TopMargin": 24.4506,
            "BottomMargin": -24.4506,
            "Tag": 2003,
            "ActionTag": 478460844,
            "Size": {
              "X": 4000.0,
              "Y": 1800.0
            },
            "Name": "Panel_1_0",
            "ctype": "PanelObjectData"
          },
          {
            "FileData": {
              "Type": "MarkedSubImage",
              "Path": "Mpira_wangu_mwekundu/Mpirawangumwekundu_moon.png",
              "Plist": "Mpira_wangu_mwekundu/Mpira_wangu_mwekundu.plist"
            },
            "BlendFunc": {
              "Src": 1,
              "Dst": 771
            },
            "AnchorPoint": {
              "ScaleX": 0.5,
              "ScaleY": 0.5
            },
            "Position": {
              "X": 2083.1702,
              "Y": 1579.0547
            },
            "Scale": {
              "ScaleX": 0.8541,
              "ScaleY": 0.8541
            },
            "RotationSkewX": 1.7077,
            "RotationSkewY": 1.6632,
            "CColor": {},
            "IconVisible": false,
            "PrePosition": {
              "X": 0.8137,
              "Y": 0.8773
            },
            "PreSize": {
              "X": 0.1742,
              "Y": 0.2594
            },
            "LeftMargin": 1860.1702,
            "RightMargin": 253.8298,
            "TopMargin": -12.5547,
            "BottomMargin": 1345.5547,
            "UserData": "main.night",
            "Tag": 1998,
            "ActionTag": 757041886,
            "Size": {
              "X": 446.0,
              "Y": 467.0
            },
            "Name": "moon",
            "ctype": "SpriteObjectData"
          },
          {
            "ClipAble": false,
            "ComboBoxIndex": 2,
            "SingleColor": {
              "R": 173,
              "G": 147,
              "B": 228
            },
            "FirstColor": {
              "R": 244,
              "G": 174,
              "B": 53
            },
            "EndColor": {
              "R": 251,
              "G": 212,
              "B": 84
            },
            "ColorVector": {
              "ScaleY": 1.0
            },
            "Scale9Width": 1,
            "Scale9Height": 1,
            "AnchorPoint": {
              "ScaleX": 0.5,
              "ScaleY": 0.5
            },
            "Position": {
              "X": 1207.1929,
              "Y": -308.4509
            },
            "Scale": {
              "ScaleX": 1.4637,
              "ScaleY": 1.2606
            },
            "RotationSkewX": -3.3458,
            "RotationSkewY": -2.0399,
            "CColor": {},
            "IconVisible": false,
            "PrePosition": {
              "X": 0.4716,
              "Y": -0.1714
            },
            "PreSize": {
              "X": 1.5625,
              "Y": 1.0
            },
            "LeftMargin": -792.8071,
            "RightMargin": -647.1929,
            "TopMargin": 1208.4509,
            "BottomMargin": -1208.4509,
            "Tag": 2002,
            "ActionTag": 656915679,
            "Size": {
              "X": 4000.0,
              "Y": 1800.0
            },
            "Name": "Panel_1_1",
            "ctype": "PanelObjectData"
          },
          {
            "ClipAble": false,
            "ComboBoxIndex": 2,
            "SingleColor": {
              "R": 173,
              "G": 147,
              "B": 228
            },
            "FirstColor": {
              "R": 184,
              "G": 199,
              "B": 244
            },
            "EndColor": {
              "R": 206,
              "G": 203,
              "B": 244
            },
            "ColorVector": {
              "ScaleY": 1.0
            },
            "Scale9Width": 1,
            "Scale9Height": 1,
            "AnchorPoint": {
              "ScaleX": 0.5,
              "ScaleY": 0.5
            },
            "Position": {
              "X": 1200.1714,
              "Y": 265.7455
            },
            "Scale": {
              "ScaleX": 1.4647,
              "ScaleY": 0.1729
            },
            "RotationSkewX": 1.4936,
            "RotationSkewY": 1.4663,
            "CColor": {},
            "IconVisible": false,
            "PrePosition": {
              "X": 0.4688,
              "Y": 0.1476
            },
            "PreSize": {
              "X": 1.5625,
              "Y": 1.0
            },
            "LeftMargin": -799.8286,
            "RightMargin": -640.1714,
            "TopMargin": 634.2545,
            "BottomMargin": -634.2545,
            "Tag": 2001,
            "ActionTag": -360271639,
            "Size": {
              "X": 4000.0,
              "Y": 1800.0
            },
            "Name": "Panel_1_2",
            "ctype": "PanelObjectData"
          },
          {
            "FileData": {
              "Type": "MarkedSubImage",
              "Path": "Mpira_wangu_mwekundu/MbwanaMamba_hut.png",
              "Plist": "Mpira_wangu_mwekundu/Mpira_wangu_mwekundu.plist"
            },
            "BlendFunc": {
              "Src": 1,
              "Dst": 771
            },
            "AnchorPoint": {
              "ScaleX": 0.5,
              "ScaleY": 0.5
            },
            "Position": {
              "X": 2176.0208,
              "Y": 243.634
            },
            "Scale": {
              "ScaleX": 0.4948,
              "ScaleY": 0.4948
            },
            "RotationSkewX": 1.6889,
            "RotationSkewY": 1.6719,
            "CColor": {},
            "IconVisible": false,
            "PrePosition": {
              "X": 0.85,
              "Y": 0.1354
            },
            "PreSize": {
              "X": 0.5703,
              "Y": 0.8628
            },
            "LeftMargin": 1446.0208,
            "RightMargin": -346.0208,
            "TopMargin": 779.866,
            "BottomMargin": -532.866,
            "UserData": "main.night",
            "Tag": 1997,
            "ActionTag": -347262882,
            "Size": {
              "X": 1460.0,
              "Y": 1553.0
            },
            "Name": "hut",
            "ctype": "SpriteObjectData"
          },
          {
            "FileData": {
              "Type": "MarkedSubImage",
              "Path": "Mpira_wangu_mwekundu/MbwanaMamba_hut.png",
              "Plist": "Mpira_wangu_mwekundu/Mpira_wangu_mwekundu.plist"
            },
            "BlendFunc": {
              "Src": 1,
              "Dst": 771
            },
            "AnchorPoint": {
              "ScaleX": 0.5,
              "ScaleY": 0.5
            },
            "Position": {
              "X": 103.8972,
              "Y": 750.779
            },
            "Scale": {
              "ScaleX": 0.3427,
              "ScaleY": 0.3427
            },
            "RotationSkewX": 1.6722,
            "RotationSkewY": 1.6848,
            "CColor": {},
            "IconVisible": false,
            "PrePosition": {
              "X": 0.0406,
              "Y": 0.4171
            },
            "PreSize": {
              "X": 0.5703,
              "Y": 0.8628
            },
            "LeftMargin": -626.1028,
            "RightMargin": 1726.1028,
            "TopMargin": 272.7209,
            "BottomMargin": -25.721,
            "UserData": "main.night",
            "Tag": 1999,
            "ActionTag": 1712206912,
            "Size": {
              "X": 1460.0,
              "Y": 1553.0
            },
            "Name": "hut",
            "ctype": "SpriteObjectData"
          },
          {
            "FileData": {
              "Type": "MarkedSubImage",
              "Path": "Mpira_wangu_mwekundu/MbwanaMamba_hut.png",
              "Plist": "Mpira_wangu_mwekundu/Mpira_wangu_mwekundu.plist"
            },
            "BlendFunc": {
              "Src": 1,
              "Dst": 771
            },
            "AnchorPoint": {
              "ScaleX": 0.5,
              "ScaleY": 0.5
            },
            "Position": {
              "X": 1666.6216,
              "Y": 791.8782
            },
            "Scale": {
              "ScaleX": 0.2553,
              "ScaleY": 0.2553
            },
            "RotationSkewX": 1.6068,
            "RotationSkewY": 1.6961,
            "CColor": {},
            "IconVisible": false,
            "PrePosition": {
              "X": 0.651,
              "Y": 0.4399
            },
            "PreSize": {
              "X": 0.5703,
              "Y": 0.8628
            },
            "LeftMargin": 936.6216,
            "RightMargin": 163.3784,
            "TopMargin": 231.6218,
            "BottomMargin": 15.3782,
            "UserData": "main.night",
            "Tag": 2000,
            "ActionTag": -28917437,
            "Size": {
              "X": 1460.0,
              "Y": 1553.0
            },
            "Name": "hut",
            "ctype": "SpriteObjectData"
          },
          {
            "FileData": {
              "Type": "Normal",
              "Path": "Mpira_wangu_mwekundu/bird.json",
              "Plist": ""
            },
            "StretchWidthEnable": false,
            "StretchHeightEnable": false,
            "InnerActionSpeed": 1.0,
            "AnchorPoint": {},
            "Position": {
              "X": 1663.7603,
              "Y": 928.1396
            },
            "Scale": {
              "ScaleX": 0.0824,
              "ScaleY": 0.0824
            },
            "CColor": {},
            "IconVisible": true,
            "PrePosition": {
              "X": 0.6499,
              "Y": 0.5156
            },
            "PreSize": {
              "X": 0.0,
              "Y": 0.0
            },
            "LeftMargin": 1663.7603,
            "RightMargin": 896.2397,
            "TopMargin": 871.8604,
            "BottomMargin": 928.1396,
            "UserData": "drag;fly",
            "Tag": 2511,
            "ActionTag": 866161992,
            "Size": {
              "X": 0.0,
              "Y": 0.0
            },
            "Name": "bird",
            "ctype": "ProjectNodeObjectData"
          },
          {
            "FileData": {
              "Type": "Normal",
              "Path": "Mpira_wangu_mwekundu/bird.json",
              "Plist": ""
            },
            "StretchWidthEnable": false,
            "StretchHeightEnable": false,
            "InnerActionSpeed": 1.0,
            "AnchorPoint": {},
            "Position": {
              "X": 93.3736,
              "Y": 1023.621
            },
            "Scale": {
              "ScaleX": -0.1162,
              "ScaleY": 0.1162
            },
            "RotationSkewY": 0.0043,
            "CColor": {},
            "IconVisible": true,
            "PrePosition": {
              "X": 0.0365,
              "Y": 0.5687
            },
            "PreSize": {
              "X": 0.0,
              "Y": 0.0
            },
            "LeftMargin": 93.3736,
            "RightMargin": 2466.6265,
            "TopMargin": 776.379,
            "BottomMargin": 1023.621,
            "UserData": "drag;eat",
            "Tag": 2614,
            "ActionTag": -1227334959,
            "Size": {
              "X": 0.0,
              "Y": 0.0
            },
            "Name": "bird",
            "ctype": "ProjectNodeObjectData"
          },
          {
            "FileData": {
              "Type": "Normal",
              "Path": "Mpira_wangu_mwekundu/boy.json",
              "Plist": ""
            },
            "StretchWidthEnable": false,
            "StretchHeightEnable": false,
            "InnerActionSpeed": 1.0,
            "AnchorPoint": {},
            "Position": {
              "X": 131.4918,
              "Y": -501.822
            },
            "Scale": {
              "ScaleX": -1.0859,
              "ScaleY": 1.0859
            },
            "CColor": {},
            "IconVisible": true,
            "PrePosition": {
              "X": 0.0514,
              "Y": -0.2788
            },
            "PreSize": {
              "X": 0.0,
              "Y": 0.0
            },
            "LeftMargin": 131.4918,
            "RightMargin": 2428.5083,
            "TopMargin": 2301.822,
            "BottomMargin": -501.822,
            "UserData": "drag;run",
            "Tag": 2004,
            "ActionTag": 324095046,
            "Size": {
              "X": 0.0,
              "Y": 0.0
            },
            "Name": "girl",
            "ctype": "ProjectNodeObjectData"
          }
        ],
        "Size": {
          "X": 2560.0,
          "Y": 1800.0
        },
        "Name": "Scene",
        "ctype": "SingleNodeObjectData"
      },
      "UsedResources": [
        "bird.json",
        "boy.json",
        "Mpira_wangu_mwekundu.plist",
        "Mpira_wangu_mwekundu.png"
      ],
      "ctype": "GameFileData"
    }
  },
  "Type": "Scene"
}